{
  "center": {
    "B_rank": 1,
    "C1": 5.482478580685447e-17,
    "C2": -1.1813544016498343e-17,
    "D": 2.7514024265075584e-17,
    "H_R": 0.0004953957789614432,
    "K": -5.641968469062232e-17,
    "Omega_over_K": 0.9999967928731927,
    "R_rg": 6.219062067617772,
    "critK": 5.641968469062232e-17,
    "label": "free_lambda_rank_defect",
    "lambda0": 3.6759313612884554,
    "logR": 22.940674282830344,
    "logT": 13.267354434238936,
    "logu": 16.190151456743152,
    "smin_over_smax_B": 2.1998606309035033e-18
  },
  "rows": [
    {
      "R_end_rg": 6.228589895175841,
      "R_max_rg": 6.228865697510512,
      "R_min_rg": 6.21056559660088,
      "R_start_rg": 6.2190594669020784,
      "alpha": 0.0,
      "alpha_deg": 0.0,
      "candidate": "free_lambda_rank_defect",
      "classification": "rank_inward",
      "delta_R_max_rg": 0.009806230608433886,
      "index": 0,
      "initial_H_R": 0.0004953980500114048,
      "initial_Omega_over_K": 0.9999968037812141,
      "initial_g_abs": 7585.03696909226,
      "initial_qadv_qvisc": 0.9593715378776657,
      "initial_qrad_qvisc": 0.040628462121484465,
      "initial_qvisc_sign": 1.0,
      "max_H_R": 0.0005301933492085174,
      "max_abs_Omega_over_K": 1.0000316875987607,
      "max_p_x": 0.04209554604462012,
      "message": "completed s_max",
      "min_p_x": -0.05562794488543534,
      "min_qvisc_sign": 1.0,
      "min_smin_over_smax_B": 9.922377545299376e-09,
      "n_steps": 3001,
      "p_T_rank": 0.9934965343274347,
      "p_u_rank": 0.10590492130461437,
      "p_x_initial": 0.00011817976535796271,
      "p_x_rank": -0.041818463898617785,
      "p_x_sign_changes": 29,
      "s_end": 6.001999999999561,
      "step_failed": false,
      "target_reached": false
    },
    {
      "R_end_rg": 6.21328323745331,
      "R_max_rg": 6.224158107147473,
      "R_min_rg": 6.21328323745331,
      "R_start_rg": 6.219059559496067,
      "alpha": 0.08607103160519981,
      "alpha_deg": 4.931506849315069,
      "candidate": "free_lambda_rank_defect",
      "classification": "rank_inward",
      "delta_R_max_rg": 0.005098547651406271,
      "index": 1,
      "initial_H_R": 0.0004953980705761241,
      "initial_Omega_over_K": 0.9999968034003226,
      "initial_g_abs": 5972.355062416715,
      "initial_qadv_qvisc": 0.9596779347719541,
      "initial_qrad_qvisc": 0.040322065227832146,
      "initial_qvisc_sign": 1.0,
      "max_H_R": 0.0005163880890570986,
      "max_abs_Omega_over_K": 1.0000204972619886,
      "max_p_x": 0.048450600819264264,
      "message": "completed s_max",
      "min_p_x": -0.053055523922723946,
      "min_qvisc_sign": -1.0,
      "min_smin_over_smax_B": 3.042039540465599e-09,
      "n_steps": 3001,
      "p_T_rank": 0.9989852739863424,
      "p_u_rank": 0.02004860457929586,
      "p_x_initial": 0.00015014428473525692,
      "p_x_rank": -0.04032958979280092,
      "p_x_sign_changes": 51,
      "s_end": 6.001999999999561,
      "step_failed": false,
      "target_reached": false
    },
    {
      "R_end_rg": 6.226211914668837,
      "R_max_rg": 6.227087927267024,
      "R_min_rg": 6.2099385963812725,
      "R_start_rg": 6.219059670659279,
      "alpha": 0.17214206321039963,
      "alpha_deg": 9.863013698630137,
      "candidate": "free_lambda_rank_defect",
      "classification": "rank_inward",
      "delta_R_max_rg": 0.008028256607745199,
      "index": 2,
      "initial_H_R": 0.0004953980741744876,
      "initial_Omega_over_K": 0.9999968029414921,
      "initial_g_abs": 4854.876199251801,
      "initial_qadv_qvisc": 0.9598875780149396,
      "initial_qrad_qvisc": 0.04011242198508131,
      "initial_qvisc_sign": 1.0,
      "max_H_R": 0.0005320371331223347,
      "max_abs_Omega_over_K": 1.0000341999336293,
      "max_p_x": 0.038902671482249886,
      "message": "completed s_max",
      "min_p_x": -0.0560299834895648,
      "min_qvisc_sign": 1.0,
      "min_smin_over_smax_B": 6.692934937933595e-09,
      "n_steps": 3001,
      "p_T_rank": 0.9970778761908494,
      "p_u_rank": -0.06595614499993821,
      "p_x_initial": 0.00018477463867908335,
      "p_x_rank": -0.0385421295142401,
      "p_x_sign_changes": 24,
      "s_end": 6.001999999999561,
      "step_failed": false,
      "target_reached": false
    },
    {
      "R_end_rg": 6.209253124823235,
      "R_max_rg": 6.228039044319153,
      "R_min_rg": 6.209253124823235,
      "R_start_rg": 6.219059799568737,
      "alpha": 0.25821309481559945,
      "alpha_deg": 14.794520547945206,
      "candidate": "free_lambda_rank_defect",
      "classification": "rank_inward",
      "delta_R_max_rg": 0.00897924475041556,
      "index": 3,
      "initial_H_R": 0.0004953980607798568,
      "initial_Omega_over_K": 0.99999680240812,
      "initial_g_abs": 4024.2246207642056,
      "initial_qadv_qvisc": 0.9600420304061048,
      "initial_qrad_qvisc": 0.039957969594291765,
      "initial_qvisc_sign": 1.0,
      "max_H_R": 0.0005279206205794739,
      "max_abs_Omega_over_K": 1.0000358995184684,
      "max_p_x": 0.04315785330821024,
      "message": "completed s_max",
      "min_p_x": -0.056313278748609336,
      "min_qvisc_sign": -1.0,
      "min_smin_over_smax_B": 5.820273491207096e-09,
      "n_steps": 3001,
      "p_T_rank": 0.9877884626468937,
      "p_u_rank": -0.15147257835761746,
      "p_x_initial": 0.0002230084457883774,
      "p_x_rank": -0.036469316793460466,
      "p_x_sign_changes": 27,
      "s_end": 6.001999999999561,
      "step_failed": false,
      "target_reached": false
    },
    {
      "R_end_rg": 6.212784033743279,
      "R_max_rg": 6.225063703266536,
      "R_min_rg": 6.212784033743279,
      "R_start_rg": 6.219059945270048,
      "alpha": 0.34428412642079925,
      "alpha_deg": 19.726027397260275,
      "candidate": "free_lambda_rank_defect",
      "classification": "rank_inward",
      "delta_R_max_rg": 0.006003757996488446,
      "index": 4,
      "initial_H_R": 0.0004953980304914035,
      "initial_Omega_over_K": 0.9999968018041542,
      "initial_g_abs": 3374.011958708506,
      "initial_qadv_qvisc": 0.9601621287244191,
      "initial_qrad_qvisc": 0.039837871275970924,
      "initial_qvisc_sign": 1.0,
      "max_H_R": 0.0005196150892128565,
      "max_abs_Omega_over_K": 1.0000218031327148,
      "max_p_x": 0.04803400191121677,
      "message": "completed s_max",
      "min_p_x": -0.05463850012559389,
      "min_qvisc_sign": -1.0,
      "min_smin_over_smax_B": 4.132438497102383e-09,
      "n_steps": 3001,
      "p_T_rank": 0.971185808922275,
      "p_u_rank": -0.2358675617407291,
      "p_x_initial": 0.0002661109470051694,
      "p_x_rank": -0.03412649801063332,
      "p_x_sign_changes": 65,
      "s_end": 6.001999999999561,
      "step_failed": false,
      "target_reached": false
    },
    {
      "R_end_rg": 6.21045812983551,
      "R_max_rg": 6.226673683206438,
      "R_min_rg": 6.210411622940922,
      "R_start_rg": 6.219060106684469,
      "alpha": 0.43035515802599905,
      "alpha_deg": 24.65753424657534,
      "candidate": "free_lambda_rank_defect",
      "classification": "rank_inward",
      "delta_R_max_rg": 0.007613576521968923,
      "index": 5,
      "initial_H_R": 0.000495397983533374,
      "initial_Omega_over_K": 0.9999968011340667,
      "initial_g_abs": 2844.1400554892452,
      "initial_qadv_qvisc": 0.9602594893961016,
      "initial_qrad_qvisc": 0.039740510603732584,
      "initial_qvisc_sign": 1.0,
      "max_H_R": 0.000524155452232031,
      "max_abs_Omega_over_K": 1.0000323074432609,
      "max_p_x": 0.04492216829187663,
      "message": "completed s_max",
      "min_p_x": -0.05698074415424614,
      "min_qvisc_sign": -1.0,
      "min_smin_over_smax_B": 1.117209115326862e-08,
      "n_steps": 3001,
      "p_T_rank": 0.9473928352564129,
      "p_u_rank": -0.31851626421951107,
      "p_x_initial": 0.00031586050959548896,
      "p_x_rank": -0.03153101857634652,
      "p_x_sign_changes": 44,
      "s_end": 6.001999999999561,
      "step_failed": false,
      "target_reached": false
    },
    {
      "R_end_rg": 6.210628992998852,
      "R_max_rg": 6.228024389061865,
      "R_min_rg": 6.210628992998852,
      "R_start_rg": 6.219060282616952,
      "alpha": 0.5164261896311989,
      "alpha_deg": 29.589041095890412,
      "candidate": "free_lambda_rank_defect",
      "classification": "rank_inward",
      "delta_R_max_rg": 0.008964106444913078,
      "index": 6,
      "initial_H_R": 0.0004953979202534346,
      "initial_Omega_over_K": 0.9999968004028182,
      "initial_g_abs": 2397.994166494949,
      "initial_qadv_qvisc": 0.9603411183476888,
      "initial_qrad_qvisc": 0.03965888165224436,
      "initial_qvisc_sign": 1.0,
      "max_H_R": 0.0005279466231242844,
      "max_abs_Omega_over_K": 1.0000296564025224,
      "max_p_x": 0.0397357244234449,
      "message": "completed s_max",
      "min_p_x": -0.05434929108639133,
      "min_qvisc_sign": -1.0,
      "min_smin_over_smax_B": 4.015202601484683e-09,
      "n_steps": 3001,
      "p_T_rank": 0.9165856965019005,
      "p_u_rank": -0.39880678371704736,
      "p_x_initial": 0.00037486800112472243,
      "p_x_rank": -0.028702094512253196,
      "p_x_sign_changes": 29,
      "s_end": 6.001999999999561,
      "step_failed": false,
      "target_reached": false
    },
    {
      "R_end_rg": 6.208900866275829,
      "R_max_rg": 6.228129831321083,
      "R_min_rg": 6.208900866275829,
      "R_start_rg": 6.21906047176498,
      "alpha": 0.6024972212363987,
      "alpha_deg": 34.520547945205486,
      "candidate": "free_lambda_rank_defect",
      "classification": "rank_inward",
      "delta_R_max_rg": 0.009069359556103329,
      "index": 7,
      "initial_H_R": 0.0004953978411200957,
      "initial_Omega_over_K": 0.9999967996158228,
      "initial_g_abs": 2011.8939546325134,
      "initial_qadv_qvisc": 0.9604115094939546,
      "initial_qrad_qvisc": 0.03958849050619008,
      "initial_qvisc_sign": 1.0,
      "max_H_R": 0.0005283688133605716,
      "max_abs_Omega_over_K": 1.000037619688405,
      "max_p_x": 0.04425559625312158,
      "message": "completed s_max",
      "min_p_x": -0.05713773201268051,
      "min_qvisc_sign": -1.0,
      "min_smin_over_smax_B": 5.349064848305585e-09,
      "n_steps": 3001,
      "p_T_rank": 0.8789924779356064,
      "p_u_rank": -0.4761446773181593,
      "p_x_initial": 0.00044716045843774593,
      "p_x_rank": -0.02566067018237043,
      "p_x_sign_changes": 21,
      "s_end": 6.001999999999561,
      "step_failed": false,
      "target_reached": false
    },
    {
      "R_end_rg": 6.227742468662126,
      "R_max_rg": 6.227742468662126,
      "R_min_rg": 6.210062894259723,
      "R_start_rg": 6.219060672728136,
      "alpha": 0.6885682528415985,
      "alpha_deg": 39.45205479452055,
      "candidate": "free_lambda_rank_defect",
      "classification": "rank_inward",
      "delta_R_max_rg": 0.008681795933989989,
      "index": 8,
      "initial_H_R": 0.0004953977467192391,
      "initial_Omega_over_K": 0.9999967987789067,
      "initial_g_abs": 1669.7433661313044,
      "initial_qadv_qvisc": 0.9604736959995475,
      "initial_qrad_qvisc": 0.0395263040005578,
      "initial_qvisc_sign": 1.0,
      "max_H_R": 0.000531765923404219,
      "max_abs_Omega_over_K": 1.0000337036262836,
      "max_p_x": 0.042731715960413696,
      "message": "completed s_max",
      "min_p_x": -0.05344021467938576,
      "min_qvisc_sign": -1.0,
      "min_smin_over_smax_B": 8.932807876367325e-09,
      "n_steps": 3001,
      "p_T_rank": 0.834891506595086,
      "p_u_rank": -0.5499573623167723,
      "p_x_initial": 0.0005393276946380294,
      "p_x_rank": -0.02242926322833595,
      "p_x_sign_changes": 26,
      "s_end": 6.001999999999561,
      "step_failed": false,
      "target_reached": false
    },
    {
      "R_end_rg": 6.2161839850031555,
      "R_max_rg": 6.223040794708937,
      "R_min_rg": 6.214545946877384,
      "R_start_rg": 6.219060884018553,
      "alpha": 0.7746392844467983,
      "alpha_deg": 44.38356164383561,
      "candidate": "free_lambda_rank_defect",
      "classification": "rank_inward",
      "delta_R_max_rg": 0.003979910690383726,
      "index": 9,
      "initial_H_R": 0.0004953976377497835,
      "initial_Omega_over_K": 0.9999967978982661,
      "initial_g_abs": 1360.1123404334062,
      "initial_qadv_qvisc": 0.9605298180305288,
      "initial_qrad_qvisc": 0.03947018196943037,
      "initial_qvisc_sign": 1.0,
      "max_H_R": 0.0005128017569629048,
      "max_abs_Omega_over_K": 1.0000155473791834,
      "max_p_x": 0.04655306379857074,
      "message": "completed s_max",
      "min_p_x": -0.0498394361465238,
      "min_qvisc_sign": -1.0,
      "min_smin_over_smax_B": 6.825691545671447e-09,
      "n_steps": 3001,
      "p_T_rank": 0.784609290642572,
      "p_u_rank": -0.6196983554179427,
      "p_x_initial": 0.0006629890502321805,
      "p_x_rank": -0.019031797856667594,
      "p_x_sign_changes": 78,
      "s_end": 6.001999999999561,
      "step_failed": false,
      "target_reached": false
    },
    {
      "R_end_rg": 6.228250327169622,
      "R_max_rg": 6.228250327169622,
      "R_min_rg": 6.211066327135853,
      "R_start_rg": 6.219061104071962,
      "alpha": 0.8607103160519981,
      "alpha_deg": 49.31506849315068,
      "candidate": "free_lambda_rank_defect",
      "classification": "rank_inward",
      "delta_R_max_rg": 0.00918922309766046,
      "index": 10,
      "initial_H_R": 0.0004953975150185142,
      "initial_Omega_over_K": 0.999996796980421,
      "initial_g_abs": 1074.545635764158,
      "initial_qadv_qvisc": 0.9605814490076565,
      "initial_qrad_qvisc": 0.03941855099237618,
      "initial_qvisc_sign": 1.0,
      "max_H_R": 0.0005287796986873861,
      "max_abs_Omega_over_K": 1.000029676487361,
      "max_p_x": 0.04637401007701244,
      "message": "completed s_max",
      "min_p_x": -0.05623106255616102,
      "min_qvisc_sign": 1.0,
      "min_smin_over_smax_B": 2.813972962396016e-09,
      "n_steps": 3001,
      "p_T_rank": 0.7285181020127776,
      "p_u_rank": -0.6848513187089762,
      "p_x_initial": 0.0008407775524231345,
      "p_x_rank": -0.015493427712308664,
      "p_x_sign_changes": 36,
      "s_end": 6.001999999999561,
      "step_failed": false,
      "target_reached": false
    },
    {
      "R_end_rg": 6.216196352787133,
      "R_max_rg": 6.225470945827946,
      "R_min_rg": 6.213477432447206,
      "R_start_rg": 6.219061331259131,
      "alpha": 0.9467813476571979,
      "alpha_deg": 54.24657534246575,
      "candidate": "free_lambda_rank_defect",
      "classification": "rank_inward",
      "delta_R_max_rg": 0.0064096145688150585,
      "index": 11,
      "initial_H_R": 0.0004953973794340987,
      "initial_Omega_over_K": 0.9999967960321663,
      "initial_g_abs": 806.5296774752609,
      "initial_qadv_qvisc": 0.960629793403639,
      "initial_qrad_qvisc": 0.039370206596378944,
      "initial_qvisc_sign": 1.0,
      "max_H_R": 0.0005206451460284974,
      "max_abs_Omega_over_K": 1.0000199098808256,
      "max_p_x": 0.04686347782693043,
      "message": "completed s_max",
      "min_p_x": -0.04869455441465469,
      "min_qvisc_sign": -1.0,
      "min_smin_over_smax_B": 6.144981889494365e-09,
      "n_steps": 3001,
      "p_T_rank": 0.6670332202417373,
      "p_u_rank": -0.7449338824446823,
      "p_x_initial": 0.0011235181891413632,
      "p_x_rank": -0.0118403496498412,
      "p_x_sign_changes": 49,
      "s_end": 6.001999999999561,
      "step_failed": false,
      "target_reached": false
    },
    {
      "R_end_rg": 6.2277438006686205,
      "R_max_rg": 6.2277438006686205,
      "R_min_rg": 6.2113478217534785,
      "R_start_rg": 6.219061563898026,
      "alpha": 1.0328523792623978,
      "alpha_deg": 59.178082191780824,
      "candidate": "free_lambda_rank_defect",
      "classification": "rank_inward",
      "delta_R_max_rg": 0.008682236770594542,
      "index": 12,
      "initial_H_R": 0.0004953972320003641,
      "initial_Omega_over_K": 0.9999967950605229,
      "initial_g_abs": 550.8280677684178,
      "initial_qadv_qvisc": 0.9606758129950632,
      "initial_qrad_qvisc": 0.03932418700499365,
      "initial_qvisc_sign": 1.0,
      "max_H_R": 0.000527873980189912,
      "max_abs_Omega_over_K": 1.0000285423307709,
      "max_p_x": 0.04309451295072769,
      "message": "completed s_max",
      "min_p_x": -0.05231163858165937,
      "min_qvisc_sign": -1.0,
      "min_smin_over_smax_B": 3.884293944945674e-09,
      "n_steps": 3001,
      "p_T_rank": 0.6006098578824166,
      "p_u_rank": -0.7995012163442008,
      "p_x_initial": 0.0016540811705169215,
      "p_x_rank": -0.008099609781140146,
      "p_x_sign_changes": 44,
      "s_end": 6.001999999999561,
      "step_failed": false,
      "target_reached": false
    },
    {
      "R_end_rg": 6.21260955907462,
      "R_max_rg": 6.225711275231168,
      "R_min_rg": 6.21260955907462,
      "R_start_rg": 6.219061800266314,
      "alpha": 1.1189234108675976,
      "alpha_deg": 64.10958904109589,
      "candidate": "free_lambda_rank_defect",
      "classification": "rank_inward",
      "delta_R_max_rg": 0.006649474964854463,
      "index": 13,
      "initial_H_R": 0.000495397073808873,
      "initial_Omega_over_K": 0.999996794072684,
      "initial_g_abs": 303.0309572135559,
      "initial_qadv_qvisc": 0.9607203117560236,
      "initial_qrad_qvisc": 0.03927968824396358,
      "initial_qvisc_sign": 1.0,
      "max_H_R": 0.0005212696127511798,
      "max_abs_Omega_over_K": 1.0000221493453254,
      "max_p_x": 0.04763871198941234,
      "message": "completed s_max",
      "min_p_x": -0.051295999764131454,
      "min_qvisc_sign": 1.0,
      "min_smin_over_smax_B": 3.274714492053729e-09,
      "n_steps": 3001,
      "p_T_rank": 0.5297397902702344,
      "p_u_rank": -0.8481493229587703,
      "p_x_initial": 0.003047698348841776,
      "p_x_rank": -0.0042989032354236595,
      "p_x_sign_changes": 37,
      "s_end": 6.001999999999561,
      "step_failed": false,
      "target_reached": false
    },
    {
      "R_end_rg": 6.2161839529699146,
      "R_max_rg": 6.228355834565494,
      "R_min_rg": 6.210998816176895,
      "R_start_rg": 6.219062038613995,
      "alpha": 1.2049944424727974,
      "alpha_deg": 69.04109589041097,
      "candidate": "free_lambda_rank_defect",
      "classification": "rank_inward",
      "delta_R_max_rg": 0.009293795951498929,
      "index": 14,
      "initial_H_R": 0.0004953969060308283,
      "initial_Omega_over_K": 0.9999967930759641,
      "initial_g_abs": 59.22895065740968,
      "initial_qadv_qvisc": 0.9607639966456241,
      "initial_qrad_qvisc": 0.03923600335437628,
      "initial_qvisc_sign": 1.0,
      "max_H_R": 0.0005288389859781564,
      "max_abs_Omega_over_K": 1.000029946219866,
      "max_p_x": 0.04532051480943306,
      "message": "completed s_max",
      "min_p_x": -0.059480011792416895,
      "min_qvisc_sign": 1.0,
      "min_smin_over_smax_B": 8.68682851790242e-09,
      "n_steps": 3001,
      "p_T_rank": 0.45494771459053635,
      "p_u_rank": -0.8905180287274914,
      "p_x_initial": 0.016833485964404576,
      "p_x_rank": -0.000466369114206,
      "p_x_sign_changes": 29,
      "s_end": 6.001999999999561,
      "step_failed": false,
      "target_reached": false
    },
    {
      "R_end_rg": 6.209243011718583,
      "R_max_rg": 6.227868372828938,
      "R_min_rg": 6.209243011718583,
      "R_start_rg": 6.219062277176399,
      "alpha": 1.2910654740779972,
      "alpha_deg": 73.97260273972603,
      "candidate": "free_lambda_rank_defect",
      "classification": "immediate_turnback",
      "delta_R_max_rg": 0.008806095652539092,
      "index": 15,
      "initial_H_R": 0.0004953967299084077,
      "initial_Omega_over_K": 0.9999967920777415,
      "initial_g_abs": 184.24363434453508,
      "initial_qadv_qvisc": 0.9608075248104012,
      "initial_qrad_qvisc": 0.0391924751896064,
      "initial_qvisc_sign": 1.0,
      "max_H_R": 0.0005275191252206076,
      "max_abs_Omega_over_K": 1.000036195511198,
      "max_p_x": 0.04283260134104832,
      "message": "completed s_max",
      "min_p_x": -0.05464432379740241,
      "min_qvisc_sign": -1.0,
      "min_smin_over_smax_B": 2.7064079116378383e-09,
      "n_steps": 3001,
      "p_T_rank": 0.3767873652042099,
      "p_u_rank": -0.9262936505763583,
      "p_x_initial": -0.004584805086647554,
      "p_x_rank": 0.003369617840765048,
      "p_x_sign_changes": 32,
      "s_end": 6.001999999999561,
      "step_failed": false,
      "target_reached": false
    },
    {
      "R_end_rg": 6.209323113821853,
      "R_max_rg": 6.2278022834505995,
      "R_min_rg": 6.209323113821853,
      "R_start_rg": 6.219062514187334,
      "alpha": 1.377136505683197,
      "alpha_deg": 78.9041095890411,
      "candidate": "free_lambda_rank_defect",
      "classification": "immediate_turnback",
      "delta_R_max_rg": 0.008739769263265806,
      "index": 16,
      "initial_H_R": 0.0004953965467455707,
      "initial_Omega_over_K": 0.9999967910854072,
      "initial_g_abs": 431.0323980326579,
      "initial_qadv_qvisc": 0.9608515440037105,
      "initial_qrad_qvisc": 0.03914845599635272,
      "initial_qvisc_sign": 1.0,
      "max_H_R": 0.0005273992842655999,
      "max_abs_Omega_over_K": 1.0000358739513193,
      "max_p_x": 0.0435433960555736,
      "message": "completed s_max",
      "min_p_x": -0.05775953185401783,
      "min_qvisc_sign": -1.0,
      "min_smin_over_smax_B": 1.6425617110854906e-09,
      "n_steps": 3001,
      "p_T_rank": 0.29583741399221153,
      "p_u_rank": -0.9552113183179908,
      "p_x_initial": -0.0020278225368075076,
      "p_x_rank": 0.00718065732416862,
      "p_x_sign_changes": 40,
      "s_end": 6.001999999999561,
      "step_failed": false,
      "target_reached": false
    },
    {
      "R_end_rg": 6.221823718468526,
      "R_max_rg": 6.224506096993416,
      "R_min_rg": 6.2143167676748785,
      "R_start_rg": 6.219062747892005,
      "alpha": 1.4632075372883968,
      "alpha_deg": 83.83561643835617,
      "candidate": "free_lambda_rank_defect",
      "classification": "immediate_turnback",
      "delta_R_max_rg": 0.005443349101410533,
      "index": 17,
      "initial_H_R": 0.000495396357898395,
      "initial_Omega_over_K": 0.9999967901063083,
      "initial_g_abs": 684.9845160167457,
      "initial_qadv_qvisc": 0.9608967318937289,
      "initial_qrad_qvisc": 0.03910326810628372,
      "initial_qvisc_sign": 1.0,
      "max_H_R": 0.0005179115799651581,
      "max_abs_Omega_over_K": 1.000016485860958,
      "max_p_x": 0.04541726209621833,
      "message": "completed s_max",
      "min_p_x": -0.04731061228013786,
      "min_qvisc_sign": 1.0,
      "min_smin_over_smax_B": 7.620083145428969e-09,
      "n_steps": 3001,
      "p_T_rank": 0.2126971860714186,
      "p_u_rank": -0.9770569356578315,
      "p_x_initial": -0.0012876164933649094,
      "p_x_rank": 0.01093853373303499,
      "p_x_sign_changes": 72,
      "s_end": 6.001999999999561,
      "step_failed": false,
      "target_reached": false
    },
    {
      "R_end_rg": 6.2101821634749665,
      "R_max_rg": 6.22723697024072,
      "R_min_rg": 6.2101821634749665,
      "R_start_rg": 6.2190629765601875,
      "alpha": 1.5492785688935966,
      "alpha_deg": 88.76712328767123,
      "candidate": "free_lambda_rank_defect",
      "classification": "immediate_turnback",
      "delta_R_max_rg": 0.008173993680532732,
      "index": 18,
      "initial_H_R": 0.0004953961647650475,
      "initial_Omega_over_K": 0.9999967891476931,
      "initial_g_abs": 950.3971440461946,
      "initial_qadv_qvisc": 0.960943839328271,
      "initial_qrad_qvisc": 0.03905616067184039,
      "initial_qvisc_sign": 1.0,
      "max_H_R": 0.0005258061389472985,
      "max_abs_Omega_over_K": 1.0000322287642216,
      "max_p_x": 0.04675464003698102,
      "message": "completed s_max",
      "min_p_x": -0.05271556601556069,
      "min_qvisc_sign": -1.0,
      "min_smin_over_smax_B": 4.336131329098126e-09,
      "n_steps": 3001,
      "p_T_rank": 0.1279822226011506,
      "p_u_rank": -0.9916687652882051,
      "p_x_initial": -0.000931952219222085,
      "p_x_rank": 0.01461542506519819,
      "p_x_sign_changes": 36,
      "s_end": 6.001999999999561,
      "step_failed": false,
      "target_reached": false
    },
    {
      "R_end_rg": 6.2277050169474055,
      "R_max_rg": 6.2277050169474055,
      "R_min_rg": 6.2115549159953085,
      "R_start_rg": 6.219063198498886,
      "alpha": 1.6353496004987964,
      "alpha_deg": 93.6986301369863,
      "candidate": "free_lambda_rank_defect",
      "classification": "immediate_turnback",
      "delta_R_max_rg": 0.008641818448519523,
      "index": 19,
      "initial_H_R": 0.0004953959687754229,
      "initial_Omega_over_K": 0.9999967882166594,
      "initial_g_abs": 1232.3267783262866,
      "initial_qadv_qvisc": 0.9609937434078505,
      "initial_qrad_qvisc": 0.03900625659221755,
      "initial_qvisc_sign": 1.0,
      "max_H_R": 0.0005271719619421626,
      "max_abs_Omega_over_K": 1.0000277067680043,
      "max_p_x": 0.04357582431373853,
      "message": "completed s_max",
      "min_p_x": -0.054815716319345176,
      "min_qvisc_sign": -1.0,
      "min_smin_over_smax_B": 3.517127188979831e-09,
      "n_steps": 3001,
      "p_T_rank": 0.042319723531783524,
      "p_u_rank": -0.9989386263347579,
      "p_x_initial": -0.0007205179516204055,
      "p_x_rank": 0.018184108903665962,
      "p_x_sign_changes": 42,
      "s_end": 6.001999999999561,
      "step_failed": false,
      "target_reached": false
    },
    {
      "R_end_rg": 6.218843075937084,
      "R_max_rg": 6.221430455256745,
      "R_min_rg": 6.217079101407028,
      "R_start_rg": 6.219063412064952,
      "alpha": 1.7214206321039962,
      "alpha_deg": 98.63013698630137,
      "candidate": "free_lambda_rank_defect",
      "classification": "immediate_turnback",
      "delta_R_max_rg": 0.002367043191792817,
      "index": 20,
      "initial_H_R": 0.000495395771380563,
      "initial_Omega_over_K": 0.9999967873201006,
      "initial_g_abs": 1537.0124676644455,
      "initial_qadv_qvisc": 0.9610475192657367,
      "initial_qrad_qvisc": 0.03895248073425844,
      "initial_qvisc_sign": 1.0,
      "max_H_R": 0.0005072014873973756,
      "max_abs_Omega_over_K": 1.0000050995689824,
      "max_p_x": 0.04865386782941953,
      "message": "completed s_max",
      "min_p_x": -0.048114170881895256,
      "min_qvisc_sign": -1.0,
      "min_smin_over_smax_B": 4.8165871845045134e-09,
      "n_steps": 3001,
      "p_T_rank": -0.043656095964244405,
      "p_u_rank": -0.9988126952898018,
      "p_x_initial": -0.0005786362239338823,
      "p_x_rank": 0.02161816396187091,
      "p_x_sign_changes": 116,
      "s_end": 6.001999999999561,
      "step_failed": false,
      "target_reached": false
    },
    {
      "R_end_rg": 6.223016790032299,
      "R_max_rg": 6.226501015279764,
      "R_min_rg": 6.210608147169783,
      "R_start_rg": 6.219063615677207,
      "alpha": 1.807491663709196,
      "alpha_deg": 103.56164383561644,
      "candidate": "free_lambda_rank_defect",
      "classification": "immediate_turnback",
      "delta_R_max_rg": 0.007437399602556738,
      "index": 21,
      "initial_H_R": 0.0004953955740419103,
      "initial_Omega_over_K": 0.9999967864646537,
      "initial_g_abs": 1872.4921102450812,
      "initial_qadv_qvisc": 0.9611065436401159,
      "initial_qrad_qvisc": 0.038893456360000606,
      "initial_qvisc_sign": 1.0,
      "max_H_R": 0.000530175218905997,
      "max_abs_Omega_over_K": 1.0000315180422312,
      "max_p_x": 0.047407917604826,
      "message": "completed s_max",
      "min_p_x": -0.054150813345352475,
      "min_qvisc_sign": -1.0,
      "min_smin_over_smax_B": 3.865815783655515e-09,
      "n_steps": 3001,
      "p_T_rank": -0.12930870099967712,
      "p_u_rank": -0.9912919045027342,
      "p_x_initial": -0.000475529162677355,
      "p_x_rank": 0.024892165697632234,
      "p_x_sign_changes": 41,
      "s_end": 6.001999999999561,
      "step_failed": false,
      "target_reached": false
    },
    {
      "R_end_rg": 6.2127176999127185,
      "R_max_rg": 6.226163091782535,
      "R_min_rg": 6.2109944673447215,
      "R_start_rg": 6.219063807828164,
      "alpha": 1.8935626953143958,
      "alpha_deg": 108.4931506849315,
      "candidate": "free_lambda_rank_defect",
      "classification": "immediate_turnback",
      "delta_R_max_rg": 0.007099283954371316,
      "index": 22,
      "initial_H_R": 0.0004953953782204888,
      "initial_Omega_over_K": 0.9999967856566534,
      "initial_g_abs": 2249.5517095406203,
      "initial_qadv_qvisc": 0.9611726531538326,
      "initial_qrad_qvisc": 0.03882734684574869,
      "initial_qvisc_sign": 1.0,
      "max_H_R": 0.000522762619966163,
      "max_abs_Omega_over_K": 1.0000299677947924,
      "max_p_x": 0.04690823291824018,
      "message": "completed s_max",
      "min_p_x": -0.050637618510004506,
      "min_qvisc_sign": 1.0,
      "min_smin_over_smax_B": 3.7790282972499034e-09,
      "n_steps": 3001,
      "p_T_rank": -0.2140039496540419,
      "p_u_rank": -0.9764319352772493,
      "p_x_initial": -0.00039618208674104135,
      "p_x_rank": 0.02798187454757077,
      "p_x_sign_changes": 49,
      "s_end": 6.001999999999561,
      "step_failed": false,
      "target_reached": false
    },
    {
      "R_end_rg": 6.2172887784307695,
      "R_max_rg": 6.221355186120819,
      "R_min_rg": 6.21706060038646,
      "R_start_rg": 6.2190639870952165,
      "alpha": 1.9796337269195956,
      "alpha_deg": 113.42465753424658,
      "candidate": "free_lambda_rank_defect",
      "classification": "immediate_turnback",
      "delta_R_max_rg": 0.002291199025602708,
      "index": 23,
      "initial_H_R": 0.0004953951853660906,
      "initial_Omega_over_K": 0.9999967849020811,
      "initial_g_abs": 2683.2660131112552,
      "initial_qadv_qvisc": 0.9612483992867438,
      "initial_qrad_qvisc": 0.038751600713035794,
      "initial_qvisc_sign": 1.0,
      "max_H_R": 0.0005067528215642595,
      "max_abs_Omega_over_K": 1.0000051723319456,
      "max_p_x": 0.04748564496109017,
      "message": "completed s_max",
      "min_p_x": -0.04637693850477775,
      "min_qvisc_sign": -1.0,
      "min_smin_over_smax_B": 9.334070015098786e-09,
      "n_steps": 3001,
      "p_T_rank": -0.29711478793856233,
      "p_u_rank": -0.9543428056264469,
      "p_x_initial": -0.00033238570569022943,
      "p_x_rank": 0.030864415388355597,
      "p_x_sign_changes": 92,
      "s_end": 6.001999999999561,
      "step_failed": false,
      "target_reached": false
    },
    {
      "R_end_rg": 6.217075993941095,
      "R_max_rg": 6.224908261541108,
      "R_min_rg": 6.212424402880741,
      "R_start_rg": 6.219064152151147,
      "alpha": 2.0657047585247956,
      "alpha_deg": 118.35616438356165,
      "candidate": "free_lambda_rank_defect",
      "classification": "immediate_turnback",
      "delta_R_max_rg": 0.005844109389960828,
      "index": 24,
      "initial_H_R": 0.0004953949969065375,
      "initial_Omega_over_K": 0.9999967842065238,
      "initial_g_abs": 3195.628744984602,
      "initial_qadv_qvisc": 0.9613374801309347,
      "initial_qrad_qvisc": 0.03866251986937422,
      "initial_qvisc_sign": 1.0,
      "max_H_R": 0.0005239316707364139,
      "max_abs_Omega_over_K": 1.0000241970880364,
      "max_p_x": 0.046835108477975854,
      "message": "completed s_max",
      "min_p_x": -0.050400110001413694,
      "min_qvisc_sign": -1.0,
      "min_smin_over_smax_B": 5.420375593916643e-09,
      "n_steps": 3001,
      "p_T_rank": -0.3780258922845035,
      "p_u_rank": -0.9251880557379549,
      "p_x_initial": -0.0002792617204775593,
      "p_x_rank": 0.033518446896113836,
      "p_x_sign_changes": 65,
      "s_end": 6.001999999999561,
      "step_failed": false,
      "target_reached": false
    },
    {
      "R_end_rg": 6.209005502945205,
      "R_max_rg": 6.228003979710995,
      "R_min_rg": 6.209005502945205,
      "R_start_rg": 6.219064301773901,
      "alpha": 2.1517757901299954,
      "alpha_deg": 123.28767123287672,
      "candidate": "free_lambda_rank_defect",
      "classification": "immediate_turnback",
      "delta_R_max_rg": 0.008939677937093826,
      "index": 25,
      "initial_H_R": 0.0004953948142371106,
      "initial_Omega_over_K": 0.9999967835751317,
      "initial_g_abs": 3820.3189039384547,
      "initial_qadv_qvisc": 0.9614455155090401,
      "initial_qrad_qvisc": 0.038554484491133516,
      "initial_qvisc_sign": 1.0,
      "max_H_R": 0.0005277855108685049,
      "max_abs_Omega_over_K": 1.0000372765002092,
      "max_p_x": 0.04118387136107804,
      "message": "completed s_max",
      "min_p_x": -0.05807588328120641,
      "min_qvisc_sign": -1.0,
      "min_smin_over_smax_B": 3.7335338659597965e-09,
      "n_steps": 3001,
      "p_T_rank": -0.45613822518359254,
      "p_u_rank": -0.8891835371795987,
      "p_x_initial": -0.00023371781535032793,
      "p_x_rank": 0.03592431955012598,
      "p_x_sign_changes": 26,
      "s_end": 6.001999999999561,
      "step_failed": false,
      "target_reached": false
    },
    {
      "R_end_rg": 6.210380940988877,
      "R_max_rg": 6.227693843574027,
      "R_min_rg": 6.209249859100214,
      "R_start_rg": 6.2190644348557695,
      "alpha": 2.2378468217351952,
      "alpha_deg": 128.21917808219177,
      "candidate": "free_lambda_rank_defect",
      "classification": "immediate_turnback",
      "delta_R_max_rg": 0.008629408718257459,
      "index": 26,
      "initial_H_R": 0.0004953946387102254,
      "initial_Omega_over_K": 0.9999967830125787,
      "initial_g_abs": 4611.96437133345,
      "initial_qadv_qvisc": 0.9615815363651402,
      "initial_qrad_qvisc": 0.038418463635086206,
      "initial_qvisc_sign": 1.0,
      "max_H_R": 0.0005270587227017544,
      "max_abs_Omega_over_K": 1.0000369524385102,
      "max_p_x": 0.03834639535813076,
      "message": "completed s_max",
      "min_p_x": -0.055127674895766914,
      "min_qvisc_sign": -1.0,
      "min_smin_over_smax_B": 1.1290004546317358e-08,
      "n_steps": 3001,
      "p_T_rank": -0.530873470252145,
      "p_u_rank": -0.8465958148099112,
      "p_x_initial": -0.0001936875238809436,
      "p_x_rank": 0.03806422111100247,
      "p_x_sign_changes": 27,
      "s_end": 6.001999999999561,
      "step_failed": false,
      "target_reached": false
    },
    {
      "R_end_rg": 6.226971921280301,
      "R_max_rg": 6.226971921280301,
      "R_min_rg": 6.210705234093487,
      "R_start_rg": 6.219064550411422,
      "alpha": 2.323917853340395,
      "alpha_deg": 133.15068493150685,
      "candidate": "free_lambda_rank_defect",
      "classification": "immediate_turnback",
      "delta_R_max_rg": 0.007907370868879049,
      "index": 27,
      "initial_H_R": 0.0004953944716254105,
      "initial_Omega_over_K": 0.9999967825230306,
      "initial_g_abs": 5665.797378258711,
      "initial_qadv_qvisc": 0.9617610992055357,
      "initial_qrad_qvisc": 0.0382389007948529,
      "initial_qvisc_sign": 1.0,
      "max_H_R": 0.0005300943903891514,
      "max_abs_Omega_over_K": 1.0000311308067806,
      "max_p_x": 0.04460837112838439,
      "message": "completed s_max",
      "min_p_x": -0.05124373032888308,
      "min_qvisc_sign": 1.0,
      "min_smin_over_smax_B": 1.0625377251892905e-08,
      "n_steps": 3001,
      "p_T_rank": -0.6016783138832356,
      "p_u_rank": -0.7977401932251849,
      "p_x_initial": -0.00015772567559245703,
      "p_x_rank": 0.0399223084962723,
      "p_x_sign_changes": 41,
      "s_end": 6.001999999999561,
      "step_failed": false,
      "target_reached": false
    },
    {
      "R_end_rg": 6.211890358964212,
      "R_max_rg": 6.226811119393055,
      "R_min_rg": 6.210255411731325,
      "R_start_rg": 6.219064647585332,
      "alpha": 2.409988884945595,
      "alpha_deg": 138.08219178082194,
      "candidate": "free_lambda_rank_defect",
      "classification": "immediate_turnback",
      "delta_R_max_rg": 0.007746471807722699,
      "index": 28,
      "initial_H_R": 0.0004953943142196947,
      "initial_Omega_over_K": 0.999996782110112,
      "initial_g_abs": 7164.466320980406,
      "initial_qadv_qvisc": 0.9620135602579317,
      "initial_qrad_qvisc": 0.03798643974271791,
      "initial_qvisc_sign": 1.0,
      "max_H_R": 0.0005245684214371145,
      "max_abs_Omega_over_K": 1.0000329337939549,
      "max_p_x": 0.04623898428025232,
      "message": "completed s_max",
      "min_p_x": -0.054880757405578275,
      "min_qvisc_sign": -1.0,
      "min_smin_over_smax_B": 3.4252869483012818e-09,
      "n_steps": 3001,
      "p_T_rank": -0.6680285417870541,
      "p_u_rank": -0.7429783823545549,
      "p_x_initial": -0.00012477867858233312,
      "p_x_rank": 0.04148482507702248,
      "p_x_sign_changes": 37,
      "s_end": 6.001999999999561,
      "step_failed": false,
      "target_reached": false
    },
    {
      "R_end_rg": 6.226780873177181,
      "R_max_rg": 6.2280260872236335,
      "R_min_rg": 6.211281471512704,
      "R_start_rg": 6.21906472565806,
      "alpha": 2.4960599165507946,
      "alpha_deg": 143.013698630137,
      "candidate": "free_lambda_rank_defect",
      "classification": "immediate_turnback",
      "delta_R_max_rg": 0.008961361565573256,
      "index": 29,
      "initial_H_R": 0.0004953941676584444,
      "initial_Omega_over_K": 0.9999967817768795,
      "initial_g_abs": 9508.89676644563,
      "initial_qadv_qvisc": 0.9624018514231482,
      "initial_qrad_qvisc": 0.03759814857608685,
      "initial_qvisc_sign": 1.0,
      "max_H_R": 0.0005281663922262069,
      "max_abs_Omega_over_K": 1.0000288107191182,
      "max_p_x": 0.045979793564495414,
      "message": "completed s_max",
      "min_p_x": -0.052778219622230366,
      "min_qvisc_sign": -1.0,
      "min_smin_over_smax_B": 5.4554336217266804e-09,
      "n_steps": 3001,
      "p_T_rank": -0.7294329200901032,
      "p_u_rank": -0.6827158194862356,
      "p_x_initial": -9.404675375109388e-05,
      "p_x_rank": 0.042740202527165594,
      "p_x_sign_changes": 44,
      "s_end": 6.001999999999561,
      "step_failed": false,
      "target_reached": false
    },
    {
      "R_end_rg": 6.219813856533877,
      "R_max_rg": 6.221707516757621,
      "R_min_rg": 6.216748946072874,
      "R_start_rg": 6.219064784051587,
      "alpha": 2.5821309481559944,
      "alpha_deg": 147.94520547945206,
      "candidate": "free_lambda_rank_defect",
      "classification": "immediate_turnback",
      "delta_R_max_rg": 0.002642732706034323,
      "index": 30,
      "initial_H_R": 0.0004953940330267386,
      "initial_Omega_over_K": 0.9999967815258003,
      "initial_g_abs": 13784.502309103196,
      "initial_qadv_qvisc": 0.9630898978046858,
      "initial_qrad_qvisc": 0.03691010219545445,
      "initial_qvisc_sign": 1.0,
      "max_H_R": 0.0005076160774577466,
      "max_abs_Omega_over_K": 1.00000646023492,
      "max_p_x": 0.04871333995556878,
      "message": "completed s_max",
      "min_p_x": -0.047132768127480046,
      "min_qvisc_sign": -1.0,
      "min_smin_over_smax_B": 7.615721247475684e-09,
      "n_steps": 3001,
      "p_T_rank": -0.7854368322589287,
      "p_u_rank": -0.6173986675516883,
      "p_x_initial": -6.489699978931808e-05,
      "p_x_rank": 0.04367914647127869,
      "p_x_sign_changes": 95,
      "s_end": 6.001999999999561,
      "step_failed": false,
      "target_reached": false
    },
    {
      "R_end_rg": 6.225067237379509,
      "R_max_rg": 6.227119405503787,
      "R_min_rg": 6.209904091264535,
      "R_start_rg": 6.219064822333587,
      "alpha": 2.668201979761194,
      "alpha_deg": 152.87671232876713,
      "candidate": "free_lambda_rank_defect",
      "classification": "immediate_turnback",
      "delta_R_max_rg": 0.008054583170199692,
      "index": 31,
      "initial_H_R": 0.0004953939113213322,
      "initial_Omega_over_K": 0.9999967813587342,
      "initial_g_abs": 24313.007958467577,
      "initial_qadv_qvisc": 0.964681433647856,
      "initial_qrad_qvisc": 0.03531856635288191,
      "initial_qvisc_sign": 1.0,
      "max_H_R": 0.0005322814831439195,
      "max_abs_Omega_over_K": 1.0000343396311635,
      "max_p_x": 0.04119732802670327,
      "message": "completed s_max",
      "min_p_x": -0.053543610338388004,
      "min_qvisc_sign": 1.0,
      "min_smin_over_smax_B": 1.1950117845142425e-08,
      "n_steps": 3001,
      "p_T_rank": -0.8356256449218775,
      "p_u_rank": -0.5475105118913758,
      "p_x_initial": -3.680555913008528e-05,
      "p_x_rank": 0.04429470529690717,
      "p_x_sign_changes": 31,
      "s_end": 6.001999999999561,
      "step_failed": false,
      "target_reached": false
    },
    {
      "R_end_rg": 6.228653304092657,
      "R_max_rg": 6.228653304092657,
      "R_min_rg": 6.210250298736387,
      "R_start_rg": 6.219064840220633,
      "alpha": 2.754273011366394,
      "alpha_deg": 157.8082191780822,
      "candidate": "free_lambda_rank_defect",
      "classification": "immediate_turnback",
      "delta_R_max_rg": 0.009588463872024278,
      "index": 32,
      "initial_H_R": 0.0004953938034432796,
      "initial_Omega_over_K": 0.9999967812769174,
      "initial_g_abs": 96076.74165508842,
      "initial_qadv_qvisc": 0.9727039148975015,
      "initial_qrad_qvisc": 0.027296085098411867,
      "initial_qvisc_sign": 1.0,
      "max_H_R": 0.0005310683690744684,
      "max_abs_Omega_over_K": 1.0000329511761294,
      "max_p_x": 0.04281135907211336,
      "message": "completed s_max",
      "min_p_x": -0.05468312333373867,
      "min_qvisc_sign": -1.0,
      "min_smin_over_smax_B": 4.955446067375277e-09,
      "n_steps": 3001,
      "p_T_rank": -0.8796277776695137,
      "p_u_rank": -0.47356877995809304,
      "p_x_initial": -9.316807298284639e-06,
      "p_x_rank": 0.04458232162187114,
      "p_x_sign_changes": 25,
      "s_end": 6.001999999999561,
      "step_failed": false,
      "target_reached": false
    },
    {
      "R_end_rg": 6.22082593959235,
      "R_max_rg": 6.228465305762138,
      "R_min_rg": 6.210905106179478,
      "R_start_rg": 6.219064837580312,
      "alpha": 2.840344042971594,
      "alpha_deg": 162.73972602739727,
      "candidate": "free_lambda_rank_defect",
      "classification": "immediate_turnback",
      "delta_R_max_rg": 0.00940046818182605,
      "index": 33,
      "initial_H_R": 0.0004953937101912642,
      "initial_Omega_over_K": 0.9999967812809557,
      "initial_g_abs": 49778.518427293435,
      "initial_qadv_qvisc": 0.9492957319639894,
      "initial_qrad_qvisc": 0.05070426804120604,
      "initial_qvisc_sign": 1.0,
      "max_H_R": 0.0005290560692435141,
      "max_abs_Omega_over_K": 1.0000303222782154,
      "max_p_x": 0.04435045279279671,
      "message": "completed s_max",
      "min_p_x": -0.056376856716605674,
      "min_qvisc_sign": -1.0,
      "min_smin_over_smax_B": 2.8692457836346564e-09,
      "n_steps": 3001,
      "p_T_rank": -0.9171174541059653,
      "p_u_rank": -0.39612091046513803,
      "p_x_initial": -1.798769779394975e-05,
      "p_x_rank": 0.04453986603552866,
      "p_x_sign_changes": 24,
      "s_end": 6.001999999999561,
      "step_failed": false,
      "target_reached": false
    },
    {
      "R_end_rg": 6.222741763857726,
      "R_max_rg": 6.223357459416125,
      "R_min_rg": 6.215318264025713,
      "R_start_rg": 6.219064814432132,
      "alpha": 2.9264150745767936,
      "alpha_deg": 167.67123287671234,
      "candidate": "free_lambda_rank_defect",
      "classification": "immediate_turnback",
      "delta_R_max_rg": 0.004292644983992844,
      "index": 34,
      "initial_H_R": 0.0004953936322556793,
      "initial_Omega_over_K": 0.9999967813708196,
      "initial_g_abs": 19678.564591287824,
      "initial_qadv_qvisc": 0.956919795046364,
      "initial_qrad_qvisc": 0.043080204956119035,
      "initial_qvisc_sign": 1.0,
      "max_H_R": 0.0005142109788976266,
      "max_abs_Omega_over_K": 1.0000123774165497,
      "max_p_x": 0.04813973012735956,
      "message": "completed s_max",
      "min_p_x": -0.04862233283625807,
      "min_qvisc_sign": -1.0,
      "min_smin_over_smax_B": 5.473062829614434e-09,
      "n_steps": 3001,
      "p_T_rank": -0.9478171137833806,
      "p_u_rank": -0.3157403003416113,
      "p_x_initial": -4.551527558573033e-05,
      "p_x_rank": 0.04416765286418713,
      "p_x_sign_changes": 86,
      "s_end": 6.001999999999561,
      "step_failed": false,
      "target_reached": false
    },
    {
      "R_end_rg": 6.213475242157489,
      "R_max_rg": 6.225498219813386,
      "R_min_rg": 6.21175014606742,
      "R_start_rg": 6.219064770947482,
      "alpha": 3.0124861061819934,
      "alpha_deg": 172.60273972602738,
      "candidate": "free_lambda_rank_defect",
      "classification": "immediate_turnback",
      "delta_R_max_rg": 0.006433448865903912,
      "index": 35,
      "initial_H_R": 0.0004953935702135266,
      "initial_Omega_over_K": 0.9999967815458435,
      "initial_g_abs": 12158.98384724948,
      "initial_qadv_qvisc": 0.9584794324895624,
      "initial_qrad_qvisc": 0.04152056751030257,
      "initial_qvisc_sign": 1.0,
      "max_H_R": 0.0005207298173552368,
      "max_abs_Omega_over_K": 1.0000269215255118,
      "max_p_x": 0.04576565309347092,
      "message": "completed s_max",
      "min_p_x": -0.055351716553579386,
      "min_qvisc_sign": -1.0,
      "min_smin_over_smax_B": 5.006891729141551e-09,
      "n_steps": 3001,
      "p_T_rank": -0.9714994671623739,
      "p_u_rank": -0.2330220595021665,
      "p_x_initial": -7.368672496382736e-05,
      "p_x_rank": 0.043468437843941214,
      "p_x_sign_changes": 53,
      "s_end": 6.001999999999561,
      "step_failed": false,
      "target_reached": false
    },
    {
      "R_end_rg": 6.225520298097669,
      "R_max_rg": 6.225520298097669,
      "R_min_rg": 6.213437332011155,
      "R_start_rg": 6.219064707448346,
      "alpha": 3.098557137787193,
      "alpha_deg": 177.53424657534245,
      "candidate": "free_lambda_rank_defect",
      "classification": "immediate_turnback",
      "delta_R_max_rg": 0.006455590649323106,
      "index": 36,
      "initial_H_R": 0.0004953935245241402,
      "initial_Omega_over_K": 0.9999967818047316,
      "initial_g_abs": 8704.5776275485,
      "initial_qadv_qvisc": 0.9591586450237031,
      "initial_qrad_qvisc": 0.04084135497670845,
      "initial_qvisc_sign": 1.0,
      "max_H_R": 0.0005211563541175968,
      "max_abs_Omega_over_K": 1.00002007791727,
      "max_p_x": 0.04327177844534651,
      "message": "completed s_max",
      "min_p_x": -0.0469503573593358,
      "min_qvisc_sign": -1.0,
      "min_smin_over_smax_B": 6.946037125199471e-09,
      "n_steps": 3001,
      "p_T_rank": -0.9879891783842533,
      "p_u_rank": -0.14857860486141283,
      "p_x_initial": -0.00010296268932585916,
      "p_x_rank": 0.042447397718166996,
      "p_x_sign_changes": 59,
      "s_end": 6.001999999999561,
      "step_failed": false,
      "target_reached": false
    },
    {
      "R_end_rg": 6.216455981621219,
      "R_max_rg": 6.221382718895997,
      "R_min_rg": 6.216423348521159,
      "R_start_rg": 6.219064624404807,
      "alpha": 3.184628169392393,
      "alpha_deg": 182.46575342465755,
      "candidate": "free_lambda_rank_defect",
      "classification": "immediate_turnback",
      "delta_R_max_rg": 0.002318094491189804,
      "index": 37,
      "initial_H_R": 0.0004953934955257819,
      "initial_Omega_over_K": 0.999996782145567,
      "initial_g_abs": 6696.925384110853,
      "initial_qadv_qvisc": 0.9595432498375386,
      "initial_qrad_qvisc": 0.040456750162244454,
      "initial_qvisc_sign": 1.0,
      "max_H_R": 0.0005066843691721968,
      "max_abs_Omega_over_K": 1.000007814658929,
      "max_p_x": 0.04766105030753171,
      "message": "completed s_max",
      "min_p_x": -0.04723261820476213,
      "min_qvisc_sign": 1.0,
      "min_smin_over_smax_B": 5.5084980513088234e-09,
      "n_steps": 3001,
      "p_T_rank": -0.9971641633963747,
      "p_u_rank": -0.0630351262133452,
      "p_x_initial": -0.0001338754048315717,
      "p_x_rank": 0.04111209191072523,
      "p_x_sign_changes": 87,
      "s_end": 6.001999999999561,
      "step_failed": false,
      "target_reached": false
    },
    {
      "R_end_rg": 6.2149243780048735,
      "R_max_rg": 6.227119956267242,
      "R_min_rg": 6.209903283709796,
      "R_start_rg": 6.219064522431716,
      "alpha": 3.270699200997593,
      "alpha_deg": 187.3972602739726,
      "candidate": "free_lambda_rank_defect",
      "classification": "immediate_turnback",
      "delta_R_max_rg": 0.008055433835526316,
      "index": 38,
      "initial_H_R": 0.0004953934834331427,
      "initial_Omega_over_K": 0.9999967825658261,
      "initial_g_abs": 5368.280223295953,
      "initial_qadv_qvisc": 0.9597937908980809,
      "initial_qrad_qvisc": 0.04020620910206813,
      "initial_qvisc_sign": 1.0,
      "max_H_R": 0.0005281717508973917,
      "max_abs_Omega_over_K": 1.000034342882943,
      "max_p_x": 0.044578776719980964,
      "message": "completed s_max",
      "min_p_x": -0.05419436525321845,
      "min_qvisc_sign": -1.0,
      "min_smin_over_smax_B": 5.981481545422149e-09,
      "n_steps": 3001,
      "p_T_rank": -0.9989564938197529,
      "p_u_rank": 0.02297504245515589,
      "p_x_initial": -0.00016707075926605008,
      "p_x_rank": 0.0394724065586318,
      "p_x_sign_changes": 31,
      "s_end": 6.001999999999561,
      "step_failed": false,
      "target_reached": false
    },
    {
      "R_end_rg": 6.210515466041432,
      "R_max_rg": 6.226830780075952,
      "R_min_rg": 6.210515466041432,
      "R_start_rg": 6.219064402284042,
      "alpha": 3.3567702326027926,
      "alpha_deg": 192.32876712328766,
      "candidate": "free_lambda_rank_defect",
      "classification": "immediate_turnback",
      "delta_R_max_rg": 0.0077663777919099175,
      "index": 39,
      "initial_H_R": 0.0004953934883357527,
      "initial_Omega_over_K": 0.9999967830623978,
      "initial_g_abs": 4411.907284555491,
      "initial_qadv_qvisc": 0.9599721939953875,
      "initial_qrad_qvisc": 0.0400278060052013,
      "initial_qvisc_sign": 1.0,
      "max_H_R": 0.0005250520819075415,
      "max_abs_Omega_over_K": 1.0000310590668555,
      "max_p_x": 0.04604426701589755,
      "message": "completed s_max",
      "min_p_x": -0.0560789565333148,
      "min_qvisc_sign": 1.0,
      "min_smin_over_smax_B": 5.286532263953335e-09,
      "n_steps": 3001,
      "p_T_rank": -0.9933528998670145,
      "p_u_rank": 0.1088151119475791,
      "p_x_initial": -0.00020336825633841747,
      "p_x_rank": 0.03754048131855817,
      "p_x_sign_changes": 50,
      "s_end": 6.001999999999561,
      "step_failed": false,
      "target_reached": false
    },
    {
      "R_end_rg": 6.226889824474087,
      "R_max_rg": 6.226889824474087,
      "R_min_rg": 6.210412143415247,
      "R_start_rg": 6.2190642648513155,
      "alpha": 3.4428412642079924,
      "alpha_deg": 197.26027397260273,
      "candidate": "free_lambda_rank_defect",
      "classification": "immediate_turnback",
      "delta_R_max_rg": 0.00782555962277165,
      "index": 40,
      "initial_H_R": 0.0004953935101973139,
      "initial_Omega_over_K": 0.9999967836316052,
      "initial_g_abs": 3681.0986369827774,
      "initial_qadv_qvisc": 0.9601074312435908,
      "initial_qrad_qvisc": 0.039892568756608106,
      "initial_qvisc_sign": 1.0,
      "max_H_R": 0.0005308506970123152,
      "max_abs_Omega_over_K": 1.000032305553674,
      "max_p_x": 0.04793936119142616,
      "message": "completed s_max",
      "min_p_x": -0.05526953810573323,
      "min_qvisc_sign": -1.0,
      "min_smin_over_smax_B": 6.469168737637514e-09,
      "n_steps": 3001,
      "p_T_rank": -0.9803948685872605,
      "p_u_rank": 0.19384955242220028,
      "p_x_initial": -0.00024385161792749244,
      "p_x_rank": 0.03533061948906068,
      "p_x_sign_changes": 41,
      "s_end": 6.001999999999561,
      "step_failed": false,
      "target_reached": false
    },
    {
      "R_end_rg": 6.225292287315508,
      "R_max_rg": 6.225844151938241,
      "R_min_rg": 6.211356217505843,
      "R_start_rg": 6.219064111151034,
      "alpha": 3.528912295813192,
      "alpha_deg": 202.1917808219178,
      "candidate": "free_lambda_rank_defect",
      "classification": "immediate_turnback",
      "delta_R_max_rg": 0.0067800407872073976,
      "index": 41,
      "initial_H_R": 0.0004953935488559732,
      "initial_Omega_over_K": 0.9999967842692339,
      "initial_g_abs": 3096.7464358658594,
      "initial_qadv_qvisc": 0.9602148872781585,
      "initial_qrad_qvisc": 0.03978511272195113,
      "initial_qvisc_sign": 1.0,
      "max_H_R": 0.0005279386865461751,
      "max_abs_Omega_over_K": 1.0000285096068093,
      "max_p_x": 0.045867210775971,
      "message": "completed s_max",
      "min_p_x": -0.05175927054809444,
      "min_qvisc_sign": -1.0,
      "min_smin_over_smax_B": 5.536242012358208e-09,
      "n_steps": 3001,
      "p_T_rank": -0.9601783367104701,
      "p_u_rank": 0.2774487986326783,
      "p_x_initial": -0.000290013096660871,
      "p_x_rank": 0.03285918211396232,
      "p_x_sign_changes": 39,
      "s_end": 6.001999999999561,
      "step_failed": false,
      "target_reached": false
    },
    {
      "R_end_rg": 6.225948205773504,
      "R_max_rg": 6.22662961329016,
      "R_min_rg": 6.210463438158879,
      "R_start_rg": 6.219063942321157,
      "alpha": 3.614983327418392,
      "alpha_deg": 207.12328767123287,
      "candidate": "free_lambda_rank_defect",
      "classification": "immediate_turnback",
      "delta_R_max_rg": 0.007565670969002625,
      "index": 42,
      "initial_H_R": 0.000495393604025521,
      "initial_Omega_over_K": 0.9999967849705632,
      "initial_g_abs": 2612.3273287570073,
      "initial_qadv_qvisc": 0.9603035071499358,
      "initial_qrad_qvisc": 0.03969649285006073,
      "initial_qvisc_sign": 1.0,
      "max_H_R": 0.00053080860194611,
      "max_abs_Omega_over_K": 1.0000321011276132,
      "max_p_x": 0.04374236758052736,
      "message": "completed s_max",
      "min_p_x": -0.05239508731173393,
      "min_qvisc_sign": -1.0,
      "min_smin_over_smax_B": 9.001519384663468e-09,
      "n_steps": 3001,
      "p_T_rank": -0.9328529803655169,
      "p_u_rank": 0.3589939110088735,
      "p_x_initial": -0.00034399520897736486,
      "p_x_rank": 0.030144466850908446,
      "p_x_sign_changes": 49,
      "s_end": 6.001999999999561,
      "step_failed": false,
      "target_reached": false
    },
    {
      "R_end_rg": 6.210764296911742,
      "R_max_rg": 6.226728853243119,
      "R_min_rg": 6.210764296911742,
      "R_start_rg": 6.2190637596116405,
      "alpha": 3.701054359023592,
      "alpha_deg": 212.05479452054794,
      "candidate": "free_lambda_rank_defect",
      "classification": "immediate_turnback",
      "delta_R_max_rg": 0.007665093631478825,
      "index": 43,
      "initial_H_R": 0.0004953936752975066,
      "initial_Omega_over_K": 0.9999967857304007,
      "initial_g_abs": 2198.5924374374326,
      "initial_qadv_qvisc": 0.9603788643472124,
      "initial_qrad_qvisc": 0.03962113565299087,
      "initial_qvisc_sign": 1.0,
      "max_H_R": 0.0005242972328300741,
      "max_abs_Omega_over_K": 1.0000299240989918,
      "max_p_x": 0.04749339582699774,
      "message": "completed s_max",
      "min_p_x": -0.05247236761240095,
      "min_qvisc_sign": -1.0,
      "min_smin_over_smax_B": 6.1210701736657315e-09,
      "n_steps": 3001,
      "p_T_rank": -0.8986211069304778,
      "p_u_rank": 0.4378811580688771,
      "p_x_initial": -0.00040901897748306485,
      "p_x_rank": 0.027206572501911424,
      "p_x_sign_changes": 36,
      "s_end": 6.001999999999561,
      "step_failed": false,
      "target_reached": false
    },
    {
      "R_end_rg": 6.212064489663307,
      "R_max_rg": 6.227385631136521,
      "R_min_rg": 6.20959950340425,
      "R_start_rg": 6.219063564375182,
      "alpha": 3.7871253906287916,
      "alpha_deg": 216.986301369863,
      "candidate": "free_lambda_rank_defect",
      "classification": "immediate_turnback",
      "delta_R_max_rg": 0.008322066761338398,
      "index": 44,
      "initial_H_R": 0.0004953937621442623,
      "initial_Omega_over_K": 0.9999967865431201,
      "initial_g_abs": 1836.130279676487,
      "initial_qadv_qvisc": 0.9604446305010915,
      "initial_qrad_qvisc": 0.039555369498851245,
      "initial_qvisc_sign": 1.0,
      "max_H_R": 0.0005260484287653737,
      "max_abs_Omega_over_K": 1.0000355555853986,
      "max_p_x": 0.04148733563204404,
      "message": "completed s_max",
      "min_p_x": -0.05771196521543639,
      "min_qvisc_sign": -1.0,
      "min_smin_over_smax_B": 6.0629321994729314e-09,
      "n_steps": 3001,
      "p_T_rank": -0.8577361572195873,
      "p_u_rank": 0.5135264862356761,
      "p_x_initial": -0.0004901938456114093,
      "p_x_rank": 0.024067250208852423,
      "p_x_sign_changes": 25,
      "s_end": 6.001999999999561,
      "step_failed": false,
      "target_reached": false
    },
    {
      "R_end_rg": 6.211114298825799,
      "R_max_rg": 6.228129045518209,
      "R_min_rg": 6.211114298825799,
      "R_start_rg": 6.219063358057273,
      "alpha": 3.8731964222339914,
      "alpha_deg": 221.91780821917806,
      "candidate": "free_lambda_rank_defect",
      "classification": "immediate_turnback",
      "delta_R_max_rg": 0.009065687460935834,
      "index": 45,
      "initial_H_R": 0.0004953938639228166,
      "initial_Omega_over_K": 0.9999967874027047,
      "initial_g_abs": 1511.4471439649637,
      "initial_qadv_qvisc": 0.9605033414915229,
      "initial_qrad_qvisc": 0.03949665850819371,
      "initial_qvisc_sign": 1.0,
      "max_H_R": 0.0005282980307836558,
      "max_abs_Omega_over_K": 1.0000291670333439,
      "max_p_x": 0.04598000912431183,
      "message": "completed s_max",
      "min_p_x": -0.05875634320288741,
      "min_qvisc_sign": -1.0,
      "min_smin_over_smax_B": 4.372473145996004e-09,
      "n_steps": 3001,
      "p_T_rank": -0.8105008290961194,
      "p_u_rank": 0.585369843965495,
      "p_x_initial": -0.0005961780546824305,
      "p_x_rank": 0.02074974241563704,
      "p_x_sign_changes": 34,
      "s_end": 6.001999999999561,
      "step_failed": false,
      "target_reached": false
    },
    {
      "R_end_rg": 6.215021008193174,
      "R_max_rg": 6.22712501104929,
      "R_min_rg": 6.2098979171734605,
      "R_start_rg": 6.219063142185401,
      "alpha": 3.959267453839191,
      "alpha_deg": 226.84931506849315,
      "candidate": "free_lambda_rank_defect",
      "classification": "immediate_turnback",
      "delta_R_max_rg": 0.00806186886388982,
      "index": 46,
      "initial_H_R": 0.0004953939798796437,
      "initial_Omega_over_K": 0.9999967883027904,
      "initial_g_abs": 1214.761481847299,
      "initial_qadv_qvisc": 0.9605568246419321,
      "initial_qrad_qvisc": 0.039443175358103454,
      "initial_qvisc_sign": 1.0,
      "max_H_R": 0.0005285184527718214,
      "max_abs_Omega_over_K": 1.00003436541121,
      "max_p_x": 0.04542292910286232,
      "message": "completed s_max",
      "min_p_x": -0.057575534168805,
      "min_qvisc_sign": -1.0,
      "min_smin_over_smax_B": 6.999431740894455e-09,
      "n_steps": 3001,
      "p_T_rank": -0.757264836403313,
      "p_u_rank": 0.6528793281734814,
      "p_x_initial": -0.0007429543049883398,
      "p_x_rank": 0.01727861078927237,
      "p_x_sign_changes": 37,
      "s_end": 6.001999999999561,
      "step_failed": false,
      "target_reached": false
    },
    {
      "R_end_rg": 6.210880029020246,
      "R_max_rg": 6.228054240818429,
      "R_min_rg": 6.210880029020246,
      "R_start_rg": 6.219062918357796,
      "alpha": 4.0453384854443915,
      "alpha_deg": 231.78082191780823,
      "candidate": "free_lambda_rank_defect",
      "classification": "immediate_turnback",
      "delta_R_max_rg": 0.008991322460633278,
      "index": 47,
      "initial_H_R": 0.0004953941091562494,
      "initial_Omega_over_K": 0.9999967892367129,
      "initial_g_abs": 938.6900748183459,
      "initial_qadv_qvisc": 0.9606064511649058,
      "initial_qrad_qvisc": 0.039393548835034146,
      "initial_qvisc_sign": 1.0,
      "max_H_R": 0.0005278637874118087,
      "max_abs_Omega_over_K": 1.0000289141514942,
      "max_p_x": 0.04351653852393121,
      "message": "completed s_max",
      "min_p_x": -0.054940020127675314,
      "min_qvisc_sign": -1.0,
      "min_smin_over_smax_B": 8.694368540436448e-09,
      "n_steps": 3001,
      "p_T_rank": -0.6984223198054306,
      "p_u_rank": 0.7155551222580502,
      "p_x_initial": -0.0009637161384380931,
      "p_x_rank": 0.013679554373877918,
      "p_x_sign_changes": 24,
      "s_end": 6.001999999999561,
      "step_failed": false,
      "target_reached": false
    },
    {
      "R_end_rg": 6.228493856377618,
      "R_max_rg": 6.2286065604949865,
      "R_min_rg": 6.210785336358105,
      "R_start_rg": 6.219062688231641,
      "alpha": 4.131409517049591,
      "alpha_deg": 236.7123287671233,
      "candidate": "free_lambda_rank_defect",
      "classification": "immediate_turnback",
      "delta_R_max_rg": 0.009543872263345854,
      "index": 48,
      "initial_H_R": 0.000495394250795528,
      "initial_Omega_over_K": 0.9999967901975575,
      "initial_g_abs": 677.4248914069107,
      "initial_qadv_qvisc": 0.9606532931427637,
      "initial_qrad_qvisc": 0.03934670685714575,
      "initial_qvisc_sign": 1.0,
      "max_H_R": 0.0005294781640291935,
      "max_abs_Omega_over_K": 1.000030804357258,
      "max_p_x": 0.04563240438537694,
      "message": "completed s_max",
      "min_p_x": -0.05381771821202378,
      "min_qvisc_sign": -1.0,
      "min_smin_over_smax_B": 5.2616067014024365e-09,
      "n_steps": 3001,
      "p_T_rank": -0.6344089287081782,
      "p_u_rank": 0.7729331965681291,
      "p_x_initial": -0.001340661297121392,
      "p_x_rank": 0.009979219323954252,
      "p_x_sign_changes": 34,
      "s_end": 6.001999999999561,
      "step_failed": false,
      "target_reached": false
    },
    {
      "R_end_rg": 6.222307323029611,
      "R_max_rg": 6.227082698489854,
      "R_min_rg": 6.212087523354581,
      "R_start_rg": 6.219062453510689,
      "alpha": 4.217480548654791,
      "alpha_deg": 241.6438356164384,
      "candidate": "free_lambda_rank_defect",
      "classification": "immediate_turnback",
      "delta_R_max_rg": 0.008020244979165092,
      "index": 49,
      "initial_H_R": 0.0004953944037488411,
      "initial_Omega_over_K": 0.9999967911782106,
      "initial_g_abs": 426.18968510220725,
      "initial_qadv_qvisc": 0.9606982263314744,
      "initial_qrad_qvisc": 0.03930177366851594,
      "initial_qvisc_sign": 1.0,
      "max_H_R": 0.0005253576196933144,
      "max_abs_Omega_over_K": 1.0000255536890503,
      "max_p_x": 0.04624304282014368,
      "message": "completed s_max",
      "min_p_x": -0.05448689203788278,
      "min_qvisc_sign": -1.0,
      "min_smin_over_smax_B": 7.228906278321899e-09,
      "n_steps": 3001,
      "p_T_rank": -0.5656985958629247,
      "p_u_rank": 0.824588743916349,
      "p_x_initial": -0.0021483961319312644,
      "p_x_rank": 0.006205001625577663,
      "p_x_sign_changes": 40,
      "s_end": 6.001999999999561,
      "step_failed": false,
      "target_reached": false
    },
    {
      "R_end_rg": 6.210377696470316,
      "R_max_rg": 6.22700935990346,
      "R_min_rg": 6.210377696470316,
      "R_start_rg": 6.219062215932722,
      "alpha": 4.303551580259991,
      "alpha_deg": 246.57534246575344,
      "candidate": "free_lambda_rank_defect",
      "classification": "immediate_turnback",
      "delta_R_max_rg": 0.007947143970738146,
      "index": 50,
      "initial_H_R": 0.0004953945668837852,
      "initial_Omega_over_K": 0.9999967921714119,
      "initial_g_abs": 180.86006289665767,
      "initial_qadv_qvisc": 0.9607420013657006,
      "initial_qrad_qvisc": 0.03925799863430551,
      "initial_qvisc_sign": 1.0,
      "max_H_R": 0.0005254019987645504,
      "max_abs_Omega_over_K": 1.0000315261706152,
      "max_p_x": 0.04546385814795494,
      "message": "completed s_max",
      "min_p_x": -0.05766289786318841,
      "min_qvisc_sign": -1.0,
      "min_smin_over_smax_B": 2.039426425705809e-09,
      "n_steps": 3001,
      "p_T_rank": -0.492800028534426,
      "p_u_rank": 0.8701393247028292,
      "p_x_initial": -0.0052031342250921184,
      "p_x_rank": 0.002384844266104346,
      "p_x_sign_changes": 52,
      "s_end": 6.001999999999561,
      "step_failed": false,
      "target_reached": false
    },
    {
      "R_end_rg": 6.213865646357638,
      "R_max_rg": 6.224729830460829,
      "R_min_rg": 6.212625081050703,
      "R_start_rg": 6.219061977256688,
      "alpha": 4.389622611865191,
      "alpha_deg": 251.5068493150685,
      "candidate": "free_lambda_rank_defect",
      "classification": "rank_inward",
      "delta_R_max_rg": 0.005667853204140982,
      "index": 51,
      "initial_H_R": 0.0004953947389925758,
      "initial_Omega_over_K": 0.999996793169808,
      "initial_g_abs": 62.32220398874638,
      "initial_qadv_qvisc": 0.9607852966579086,
      "initial_qrad_qvisc": 0.03921470334207817,
      "initial_qvisc_sign": 1.0,
      "max_H_R": 0.0005184057836571101,
      "max_abs_Omega_over_K": 1.0000233805245413,
      "max_p_x": 0.046615809440007386,
      "message": "completed s_max",
      "min_p_x": -0.05123196244693721,
      "min_qvisc_sign": 1.0,
      "min_smin_over_smax_B": 2.520158462446216e-09,
      "n_steps": 3001,
      "p_T_rank": -0.41625294221021786,
      "p_u_rank": 0.9092476983641725,
      "p_x_initial": 0.011930506528022546,
      "p_x_rank": -0.001452969645931614,
      "p_x_sign_changes": 64,
      "s_end": 6.001999999999561,
      "step_failed": false,
      "target_reached": false
    },
    {
      "R_end_rg": 6.211617525713538,
      "R_max_rg": 6.227667838338276,
      "R_min_rg": 6.211587441484717,
      "R_start_rg": 6.219061739249663,
      "alpha": 4.4756936434703904,
      "alpha_deg": 256.43835616438355,
      "candidate": "free_lambda_rank_defect",
      "classification": "rank_inward",
      "delta_R_max_rg": 0.008606099088613206,
      "index": 52,
      "initial_H_R": 0.0004953949188009889,
      "initial_Omega_over_K": 0.9999967941660068,
      "initial_g_abs": 306.98549485485864,
      "initial_qadv_qvisc": 0.9608287614783607,
      "initial_qrad_qvisc": 0.03917123852159588,
      "initial_qvisc_sign": 1.0,
      "max_H_R": 0.0005271695662940278,
      "max_abs_Omega_over_K": 1.0000275766260491,
      "max_p_x": 0.04465542316695671,
      "message": "completed s_max",
      "min_p_x": -0.05557317515657772,
      "min_qvisc_sign": -1.0,
      "min_smin_over_smax_B": 1.5150276393384279e-09,
      "n_steps": 3001,
      "p_T_rank": -0.3366240647359756,
      "p_u_rank": 0.9416243201846064,
      "p_x_initial": 0.0028187024067236307,
      "p_x_rank": -0.005280026279058445,
      "p_x_sign_changes": 37,
      "s_end": 6.001999999999561,
      "step_failed": false,
      "target_reached": false
    },
    {
      "R_end_rg": 6.229141506804733,
      "R_max_rg": 6.229141506804733,
      "R_min_rg": 6.2102267016894075,
      "R_start_rg": 6.219061503673776,
      "alpha": 4.56176467507559,
      "alpha_deg": 261.36986301369865,
      "candidate": "free_lambda_rank_defect",
      "classification": "rank_inward",
      "delta_R_max_rg": 0.01008000313095625,
      "index": 53,
      "initial_H_R": 0.0004953951049777941,
      "initial_Omega_over_K": 0.9999967951526332,
      "initial_g_abs": 556.8477257056068,
      "initial_qadv_qvisc": 0.9608730552210536,
      "initial_qrad_qvisc": 0.03912694477885973,
      "initial_qvisc_sign": 1.0,
      "max_H_R": 0.0005313303932284095,
      "max_abs_Omega_over_K": 1.000033048055346,
      "max_p_x": 0.04565268913359467,
      "message": "completed s_max",
      "min_p_x": -0.057000102568764525,
      "min_qvisc_sign": -1.0,
      "min_smin_over_smax_B": 6.2811164878724495e-09,
      "n_steps": 3001,
      "p_T_rank": -0.25450294046082567,
      "p_u_rank": 0.9670294849837558,
      "p_x_initial": 0.0015783638332843648,
      "p_x_rank": -0.009067991444933782,
      "p_x_sign_changes": 34,
      "s_end": 6.001999999999561,
      "step_failed": false,
      "target_reached": false
    },
    {
      "R_end_rg": 6.2103864684967,
      "R_max_rg": 6.227678952240026,
      "R_min_rg": 6.2103864684967,
      "R_start_rg": 6.219061272273149,
      "alpha": 4.64783570668079,
      "alpha_deg": 266.3013698630137,
      "candidate": "free_lambda_rank_defect",
      "classification": "rank_inward",
      "delta_R_max_rg": 0.008617679966877567,
      "index": 54,
      "initial_H_R": 0.0004953952961446106,
      "initial_Omega_over_K": 0.9999967961223826,
      "initial_g_abs": 815.9471261512793,
      "initial_qadv_qvisc": 0.9609188879376296,
      "initial_qrad_qvisc": 0.03908111206235349,
      "initial_qvisc_sign": 1.0,
      "max_H_R": 0.0005271039133312163,
      "max_abs_Omega_over_K": 1.0000309200778996,
      "max_p_x": 0.0482248976229954,
      "message": "completed s_max",
      "min_p_x": -0.058333850800133175,
      "min_qvisc_sign": 1.0,
      "min_smin_over_smax_B": 5.871473698197122e-09,
      "n_steps": 3001,
      "p_T_rank": -0.17049756545724792,
      "p_u_rank": 0.9852751018099328,
      "p_x_initial": 0.0010835786376604854,
      "p_x_rank": -0.01278882037476188,
      "p_x_sign_changes": 37,
      "s_end": 6.001999999999561,
      "step_failed": false,
      "target_reached": false
    },
    {
      "R_end_rg": 6.217093403426891,
      "R_max_rg": 6.22695829753159,
      "R_min_rg": 6.210087753763222,
      "R_start_rg": 6.21906104676097,
      "alpha": 4.73390673828599,
      "alpha_deg": 271.2328767123288,
      "candidate": "free_lambda_rank_defect",
      "classification": "rank_inward",
      "delta_R_max_rg": 0.00789725077062009,
      "index": 55,
      "initial_H_R": 0.0004953954908861086,
      "initial_Omega_over_K": 0.9999967970680749,
      "initial_g_abs": 1088.9159114043825,
      "initial_qadv_qvisc": 0.9609670676126344,
      "initial_qrad_qvisc": 0.03903293238719364,
      "initial_qvisc_sign": 1.0,
      "max_H_R": 0.0005312699941020641,
      "max_abs_Omega_over_K": 1.0000336057657349,
      "max_p_x": 0.04580261067191329,
      "message": "completed s_max",
      "min_p_x": -0.05759279945933345,
      "min_qvisc_sign": -1.0,
      "min_smin_over_smax_B": 1.4476187945861447e-09,
      "n_steps": 3001,
      "p_T_rank": -0.0852298861308742,
      "p_u_rank": 0.9962260864997362,
      "p_x_initial": 0.0008145193648718488,
      "p_x_rank": -0.016414965352949795,
      "p_x_sign_changes": 40,
      "s_end": 6.001999999999561,
      "step_failed": false,
      "target_reached": false
    },
    {
      "R_end_rg": 6.224895014916926,
      "R_max_rg": 6.228500907073151,
      "R_min_rg": 6.210876147924522,
      "R_start_rg": 6.219060828806877,
      "alpha": 4.81997776989119,
      "alpha_deg": 276.1643835616439,
      "candidate": "free_lambda_rank_defect",
      "classification": "rank_inward",
      "delta_R_max_rg": 0.009440078266274021,
      "index": 56,
      "initial_H_R": 0.0004953956877604958,
      "initial_Omega_over_K": 0.9999967979827089,
      "initial_g_abs": 1381.339413362297,
      "initial_qadv_qvisc": 0.9610185613978968,
      "initial_qrad_qvisc": 0.038981438601992414,
      "initial_qvisc_sign": 1.0,
      "max_H_R": 0.0005293285751222286,
      "max_abs_Omega_over_K": 1.0000304408942817,
      "max_p_x": 0.045062941801979194,
      "message": "completed s_max",
      "min_p_x": -0.05350071650193007,
      "min_qvisc_sign": -1.0,
      "min_smin_over_smax_B": 3.892426584127733e-09,
      "n_steps": 3001,
      "p_T_rank": 0.0006688054530991083,
      "p_u_rank": 0.9998013617939349,
      "p_x_initial": 0.0006433664273619087,
      "p_x_rank": -0.01991957967075552,
      "p_x_sign_changes": 35,
      "s_end": 6.001999999999561,
      "step_failed": false,
      "target_reached": false
    },
    {
      "R_end_rg": 6.215046803920995,
      "R_max_rg": 6.222931176928744,
      "R_min_rg": 6.215046803920995,
      "R_start_rg": 6.219060620024501,
      "alpha": 4.9060488014963894,
      "alpha_deg": 281.09589041095893,
      "candidate": "free_lambda_rank_defect",
      "classification": "rank_inward",
      "delta_R_max_rg": 0.0038705569042427612,
      "index": 57,
      "initial_H_R": 0.0004953958853101831,
      "initial_Omega_over_K": 0.9999967988595135,
      "initial_g_abs": 1700.2624233123374,
      "initial_qadv_qvisc": 0.9610745810660085,
      "initial_qrad_qvisc": 0.03892541893369563,
      "initial_qvisc_sign": 1.0,
      "max_H_R": 0.0005126911424337697,
      "max_abs_Omega_over_K": 1.0000128581750403,
      "max_p_x": 0.047387893791903904,
      "message": "completed s_max",
      "min_p_x": -0.04678838818034474,
      "min_qvisc_sign": -1.0,
      "min_smin_over_smax_B": 5.98668691283313e-09,
      "n_steps": 3001,
      "p_T_rank": 0.08656254543549212,
      "p_u_rank": 0.9959744576051293,
      "p_x_initial": 0.0005234110198639263,
      "p_x_rank": -0.023276716389926688,
      "p_x_sign_changes": 85,
      "s_end": 6.001999999999561,
      "step_failed": false,
      "target_reached": false
    },
    {
      "R_end_rg": 6.2173056216860205,
      "R_max_rg": 6.224139636220962,
      "R_min_rg": 6.213292978594366,
      "R_start_rg": 6.219060421959597,
      "alpha": 4.992119833101589,
      "alpha_deg": 286.027397260274,
      "candidate": "free_lambda_rank_defect",
      "classification": "rank_inward",
      "delta_R_max_rg": 0.005079214261365372,
      "index": 58,
      "initial_H_R": 0.0004953960820725817,
      "initial_Omega_over_K": 0.9999967996919966,
      "initial_g_abs": 2054.9489201556908,
      "initial_qadv_qvisc": 0.9611367101750876,
      "initial_qrad_qvisc": 0.0388632898249538,
      "initial_qvisc_sign": 1.0,
      "max_H_R": 0.0005204289687975134,
      "max_abs_Omega_over_K": 1.0000206610763653,
      "max_p_x": 0.047749613837399146,
      "message": "completed s_max",
      "min_p_x": -0.04892581110842311,
      "min_qvisc_sign": -1.0,
      "min_smin_over_smax_B": 3.530286773710724e-09,
      "n_steps": 3001,
      "p_T_rank": 0.17181540661705055,
      "p_u_rank": 0.9847737069930175,
      "p_x_initial": 0.0004335157045097966,
      "p_x_rank": -0.026461520444753334,
      "p_x_sign_changes": 50,
      "s_end": 6.001999999999561,
      "step_failed": false,
      "target_reached": false
    },
    {
      "R_end_rg": 6.2258103142633505,
      "R_max_rg": 6.228839474676811,
      "R_min_rg": 6.210588058013562,
      "R_start_rg": 6.219060236078603,
      "alpha": 5.078190864706789,
      "alpha_deg": 290.958904109589,
      "candidate": "free_lambda_rank_defect",
      "classification": "rank_inward",
      "delta_R_max_rg": 0.009779238598208728,
      "index": 59,
      "initial_H_R": 0.0004953962765909321,
      "initial_Omega_over_K": 0.9999968004739953,
      "initial_g_abs": 2458.084469402906,
      "initial_qadv_qvisc": 0.9612071038215492,
      "initial_qrad_qvisc": 0.03879289617836417,
      "initial_qvisc_sign": 1.0,
      "max_H_R": 0.0005301577728777753,
      "max_abs_Omega_over_K": 1.0000315977507672,
      "max_p_x": 0.045443366668643695,
      "message": "completed s_max",
      "min_p_x": -0.05684412905689081,
      "min_qvisc_sign": -1.0,
      "min_smin_over_smax_B": 2.871575152202525e-09,
      "n_steps": 3001,
      "p_T_rank": 0.255796206640938,
      "p_u_rank": 0.966282036396334,
      "p_x_initial": 0.00036271006482422983,
      "p_x_rank": -0.02945041266027844,
      "p_x_sign_changes": 25,
      "s_end": 6.001999999999561,
      "step_failed": false,
      "target_reached": false
    },
    {
      "R_end_rg": 6.220983209120972,
      "R_max_rg": 6.22141917771197,
      "R_min_rg": 6.2169943249181125,
      "R_start_rg": 6.219060063757673,
      "alpha": 5.164261896311989,
      "alpha_deg": 295.8904109589041,
      "candidate": "free_lambda_rank_defect",
      "classification": "rank_inward",
      "delta_R_max_rg": 0.0023591139542968875,
      "index": 60,
      "initial_H_R": 0.0004953964674250815,
      "initial_Omega_over_K": 0.99999680119972,
      "initial_g_abs": 2927.774633877955,
      "initial_qadv_qvisc": 0.961288818071788,
      "initial_qrad_qvisc": 0.03871118192839378,
      "initial_qvisc_sign": 1.0,
      "max_H_R": 0.0005068405993980331,
      "max_abs_Omega_over_K": 1.000005434674815,
      "max_p_x": 0.047386131101355755,
      "message": "completed s_max",
      "min_p_x": -0.047514626875624306,
      "min_qvisc_sign": 1.0,
      "min_smin_over_smax_B": 8.740771899900424e-09,
      "n_steps": 3001,
      "p_T_rank": 0.33788318104607395,
      "p_u_rank": 0.9406363516745099,
      "p_x_initial": 0.00030472270918566674,
      "p_x_rank": -0.032221264324259605,
      "p_x_sign_changes": 79,
      "s_end": 6.001999999999561,
      "step_failed": false,
      "target_reached": false
    },
    {
      "R_end_rg": 6.217675610895675,
      "R_max_rg": 6.2222784884075155,
      "R_min_rg": 6.216260610008451,
      "R_start_rg": 6.219059906272611,
      "alpha": 5.250332927917189,
      "alpha_deg": 300.8219178082192,
      "candidate": "free_lambda_rank_defect",
      "classification": "rank_inward",
      "delta_R_max_rg": 0.0032185821349042243,
      "index": 61,
      "initial_H_R": 0.0004953966531621559,
      "initial_Omega_over_K": 0.9999968018637975,
      "initial_g_abs": 3491.0581445758835,
      "initial_qadv_qvisc": 0.9613863841233269,
      "initial_qrad_qvisc": 0.0386136158763929,
      "initial_qvisc_sign": 1.0,
      "max_H_R": 0.000510296390402708,
      "max_abs_Omega_over_K": 1.0000084889767515,
      "max_p_x": 0.047887420181244665,
      "message": "completed s_max",
      "min_p_x": -0.0471831593283909,
      "min_qvisc_sign": 1.0,
      "min_smin_over_smax_B": 5.443876906948059e-09,
      "n_steps": 3001,
      "p_T_rank": 0.41746858659366837,
      "p_u_rank": 0.9080265245045902,
      "p_x_initial": 0.00025569751375851136,
      "p_x_rank": -0.03475356102041243,
      "p_x_sign_changes": 89,
      "s_end": 6.001999999999561,
      "step_failed": false,
      "target_reached": false
    },
    {
      "R_end_rg": 6.226099772665729,
      "R_max_rg": 6.22637898051303,
      "R_min_rg": 6.210749127194465,
      "R_start_rg": 6.219059764789415,
      "alpha": 5.336403959522388,
      "alpha_deg": 305.75342465753425,
      "candidate": "free_lambda_rank_defect",
      "classification": "rank_inward",
      "delta_R_max_rg": 0.007319215723615713,
      "index": 62,
      "initial_H_R": 0.0004953968324270182,
      "initial_Omega_over_K": 0.999996802461312,
      "initial_g_abs": 4190.487530488946,
      "initial_qadv_qvisc": 0.9615068728023528,
      "initial_qrad_qvisc": 0.03849312719784952,
      "initial_qvisc_sign": 1.0,
      "max_H_R": 0.0005300391861537716,
      "max_abs_Omega_over_K": 1.000030955305803,
      "max_p_x": 0.04427553459533247,
      "message": "completed s_max",
      "min_p_x": -0.05430093287511388,
      "min_qvisc_sign": -1.0,
      "min_smin_over_smax_B": 4.340512279912717e-09,
      "n_steps": 3001,
      "p_T_rank": 0.49396320078553,
      "p_u_rank": 0.8686939866377665,
      "p_x_initial": 0.00021312181277282613,
      "p_x_rank": -0.03702855450997126,
      "p_x_sign_changes": 46,
      "s_end": 6.001999999999561,
      "step_failed": false,
      "target_reached": false
    },
    {
      "R_end_rg": 6.223034529013118,
      "R_max_rg": 6.22650174946633,
      "R_min_rg": 6.210608386228522,
      "R_start_rg": 6.219059640355537,
      "alpha": 5.422474991127588,
      "alpha_deg": 310.68493150684935,
      "candidate": "free_lambda_rank_defect",
      "classification": "rank_inward",
      "delta_R_max_rg": 0.007442109110792572,
      "index": 63,
      "initial_H_R": 0.0004953970038924432,
      "initial_Omega_over_K": 0.9999968029878393,
      "initial_g_abs": 5097.454810681227,
      "initial_qadv_qvisc": 0.9616620226558849,
      "initial_qrad_qvisc": 0.038337977343916516,
      "initial_qvisc_sign": 1.0,
      "max_H_R": 0.0005303026209092343,
      "max_abs_Omega_over_K": 1.0000315185941915,
      "max_p_x": 0.04711556099542443,
      "message": "completed s_max",
      "min_p_x": -0.053798814203492,
      "min_qvisc_sign": -1.0,
      "min_smin_over_smax_B": 5.616966780073108e-09,
      "n_steps": 3001,
      "p_T_rank": 0.5668006842612934,
      "p_u_rank": 0.8229299424231604,
      "p_x_initial": 0.00017527675006697804,
      "p_x_rank": -0.03902940153708958,
      "p_x_sign_changes": 36,
      "s_end": 6.001999999999561,
      "step_failed": false,
      "target_reached": false
    },
    {
      "R_end_rg": 6.223491247502851,
      "R_max_rg": 6.223491247502851,
      "R_min_rg": 6.214669268926986,
      "R_start_rg": 6.219059533892276,
      "alpha": 5.508546022732788,
      "alpha_deg": 315.6164383561644,
      "candidate": "free_lambda_rank_defect",
      "classification": "rank_inward",
      "delta_R_max_rg": 0.004431713610575372,
      "index": 64,
      "initial_H_R": 0.0004953971662889541,
      "initial_Omega_over_K": 0.9999968034394815,
      "initial_g_abs": 6342.023528413417,
      "initial_qadv_qvisc": 0.9618729250445973,
      "initial_qrad_qvisc": 0.03812707495607993,
      "initial_qvisc_sign": 1.0,
      "max_H_R": 0.0005167380212498623,
      "max_abs_Omega_over_K": 1.0000150434244035,
      "max_p_x": 0.04727238056440298,
      "message": "completed s_max",
      "min_p_x": -0.04805746381588549,
      "min_qvisc_sign": 1.0,
      "min_smin_over_smax_B": 5.01833191142976e-09,
      "n_steps": 3001,
      "p_T_rank": 0.6354417737768968,
      "p_u_rank": 0.7710732128327067,
      "p_x_initial": 0.00014093459269085912,
      "p_x_rank": -0.04074128853041338,
      "p_x_sign_changes": 66,
      "s_end": 6.001999999999561,
      "step_failed": false,
      "target_reached": false
    },
    {
      "R_end_rg": 6.212658301954449,
      "R_max_rg": 6.226076789357519,
      "R_min_rg": 6.211094043476333,
      "R_start_rg": 6.21905944618781,
      "alpha": 5.594617054337988,
      "alpha_deg": 320.54794520547944,
      "candidate": "free_lambda_rank_defect",
      "classification": "rank_inward",
      "delta_R_max_rg": 0.007017343169708923,
      "index": 65,
      "initial_H_R": 0.0004953973184142126,
      "initial_Omega_over_K": 0.9999968038128948,
      "initial_g_abs": 8189.343513092671,
      "initial_qadv_qvisc": 0.9621817510455258,
      "initial_qrad_qvisc": 0.03781824895426871,
      "initial_qvisc_sign": 1.0,
      "max_H_R": 0.000522648147295807,
      "max_abs_Omega_over_K": 1.0000295689181848,
      "max_p_x": 0.0468964726159294,
      "message": "completed s_max",
      "min_p_x": -0.05369481817913752,
      "min_qvisc_sign": 1.0,
      "min_smin_over_smax_B": 7.286092905496636e-09,
      "n_steps": 3001,
      "p_T_rank": 0.6993782747209711,
      "p_u_rank": 0.7135077269492199,
      "p_x_initial": 0.00010918203516249238,
      "p_x_rank": -0.04215154127758068,
      "p_x_sign_changes": 50,
      "s_end": 6.001999999999561,
      "step_failed": false,
      "target_reached": false
    },
    {
      "R_end_rg": 6.210448076288306,
      "R_max_rg": 6.226907181584142,
      "R_min_rg": 6.2101459306783635,
      "R_start_rg": 6.2190593778914955,
      "alpha": 5.680688085943188,
      "alpha_deg": 325.47945205479454,
      "candidate": "free_lambda_rank_defect",
      "classification": "rank_inward",
      "delta_R_max_rg": 0.007847803692646593,
      "index": 66,
      "initial_H_R": 0.0004953974591419265,
      "initial_Omega_over_K": 0.9999968041053148,
      "initial_g_abs": 11277.425029445687,
      "initial_qadv_qvisc": 0.9626870052423275,
      "initial_qrad_qvisc": 0.03731299475622169,
      "initial_qvisc_sign": 1.0,
      "max_H_R": 0.000524849104153723,
      "max_abs_Omega_over_K": 1.0000333724300738,
      "max_p_x": 0.04650980409463523,
      "message": "completed s_max",
      "min_p_x": -0.0556639771822184,
      "min_qvisc_sign": -1.0,
      "min_smin_over_smax_B": 1.1666773605338379e-08,
      "n_steps": 3001,
      "p_T_rank": 0.7581368236099397,
      "p_u_rank": 0.6506596794897895,
      "p_x_initial": 7.931141863701195e-05,
      "p_x_rank": -0.04324971876065544,
      "p_x_sign_changes": 36,
      "s_end": 6.001999999999561,
      "step_failed": false,
      "target_reached": false
    },
    {
      "R_end_rg": 6.2162443820099735,
      "R_max_rg": 6.2217425308794425,
      "R_min_rg": 6.216021498991947,
      "R_start_rg": 6.219059329508988,
      "alpha": 5.766759117548387,
      "alpha_deg": 330.4109589041096,
      "candidate": "free_lambda_rank_defect",
      "classification": "rank_inward",
      "delta_R_max_rg": 0.0026832013704547464,
      "index": 67,
      "initial_H_R": 0.0004953975874301888,
      "initial_Omega_over_K": 0.9999968043145762,
      "initial_g_abs": 17629.73177303751,
      "initial_qadv_qvisc": 0.9636850457017003,
      "initial_qrad_qvisc": 0.03631495429930113,
      "initial_qvisc_sign": 1.0,
      "max_H_R": 0.000508630919692734,
      "max_abs_Omega_over_K": 1.0000094832877773,
      "max_p_x": 0.04703924979774477,
      "message": "completed s_max",
      "min_p_x": -0.04903706812302901,
      "min_qvisc_sign": 1.0,
      "min_smin_over_smax_B": 7.505118804268763e-09,
      "n_steps": 3001,
      "p_T_rank": 0.8112823927056358,
      "p_u_rank": 0.5829943754092084,
      "p_x_initial": 5.075031629265395e-05,
      "p_x_rank": -0.044027690457771475,
      "p_x_sign_changes": 100,
      "s_end": 6.001999999999561,
      "step_failed": false,
      "target_reached": false
    },
    {
      "R_end_rg": 6.210649702124114,
      "R_max_rg": 6.22711188712992,
      "R_min_rg": 6.209913568883154,
      "R_start_rg": 6.219059301398461,
      "alpha": 5.852830149153587,
      "alpha_deg": 335.3424657534247,
      "candidate": "free_lambda_rank_defect",
      "classification": "rank_inward",
      "delta_R_max_rg": 0.008052585731458173,
      "index": 68,
      "initial_H_R": 0.0004953977023291844,
      "initial_Omega_over_K": 0.9999968044391305,
      "initial_g_abs": 38890.11955237006,
      "initial_qadv_qvisc": 0.9666689210489351,
      "initial_qrad_qvisc": 0.033331078952018284,
      "initial_qvisc_sign": 1.0,
      "max_H_R": 0.0005254875392697569,
      "max_abs_Omega_over_K": 1.000034303093724,
      "max_p_x": 0.04679229539388587,
      "message": "completed s_max",
      "min_p_x": -0.05465402190241336,
      "min_qvisc_sign": -1.0,
      "min_smin_over_smax_B": 4.807842004114408e-09,
      "n_steps": 3001,
      "p_T_rank": 0.858421510808474,
      "p_u_rank": 0.5110127849448823,
      "p_x_initial": 2.301334527940014e-05,
      "p_x_rank": -0.0444796965386717,
      "p_x_sign_changes": 46,
      "s_end": 6.001999999999561,
      "step_failed": false,
      "target_reached": false
    },
    {
      "R_end_rg": 6.215939111702254,
      "R_max_rg": 6.226026166211349,
      "R_min_rg": 6.21114818332598,
      "R_start_rg": 6.219059293768048,
      "alpha": 5.938901180758787,
      "alpha_deg": 340.2739726027398,
      "candidate": "free_lambda_rank_defect",
      "classification": "rank_inward",
      "delta_R_max_rg": 0.006966872443300964,
      "index": 69,
      "initial_H_R": 0.0004953978029882333,
      "initial_Omega_over_K": 0.999996804478055,
      "initial_g_abs": 206613.4538964817,
      "initial_qadv_qvisc": 0.348810424444129,
      "initial_qrad_qvisc": 0.6511895756263997,
      "initial_qvisc_sign": 1.0,
      "max_H_R": 0.0005260939473407246,
      "max_abs_Omega_over_K": 1.0000293469378403,
      "max_p_x": 0.03983188720468728,
      "message": "completed s_max",
      "min_p_x": -0.05432346818280276,
      "min_qvisc_sign": -1.0,
      "min_smin_over_smax_B": 5.291609698423044e-09,
      "n_steps": 3001,
      "p_T_rank": 0.8992051763805469,
      "p_u_rank": 0.4352478346084668,
      "p_x_initial": 4.333042086802771e-06,
      "p_x_rank": -0.04460239050847614,
      "p_x_sign_changes": 44,
      "s_end": 6.001999999999561,
      "step_failed": false,
      "target_reached": false
    },
    {
      "R_end_rg": 6.2103366739554815,
      "R_max_rg": 6.227729410611603,
      "R_min_rg": 6.2103366739554815,
      "R_start_rg": 6.2190593066742395,
      "alpha": 6.024972212363987,
      "alpha_deg": 345.20547945205476,
      "candidate": "free_lambda_rank_defect",
      "classification": "rank_inward",
      "delta_R_max_rg": 0.008670103937363116,
      "index": 70,
      "initial_H_R": 0.0004953978886620813,
      "initial_Omega_over_K": 0.9999968044310618,
      "initial_g_abs": 28251.619384076967,
      "initial_qadv_qvisc": 0.9549892157978254,
      "initial_qrad_qvisc": 0.045010784199195436,
      "initial_qvisc_sign": 1.0,
      "max_H_R": 0.0005271787723818238,
      "max_abs_Omega_over_K": 1.0000311104970785,
      "max_p_x": 0.0463583615034059,
      "message": "completed s_max",
      "min_p_x": -0.05573446889874248,
      "min_qvisc_sign": -1.0,
      "min_smin_over_smax_B": 6.385189195767918e-09,
      "n_steps": 3001,
      "p_T_rank": 0.9333314414309076,
      "p_u_rank": 0.3562604615844283,
      "p_x_initial": 3.169863208784495e-05,
      "p_x_rank": -0.04439486398395919,
      "p_x_sign_changes": 33,
      "s_end": 6.001999999999561,
      "step_failed": false,
      "target_reached": false
    },
    {
      "R_end_rg": 6.209826888458466,
      "R_max_rg": 6.227867161007706,
      "R_min_rg": 6.209826888458466,
      "R_start_rg": 6.219059340021503,
      "alpha": 6.111043243969187,
      "alpha_deg": 350.13698630136986,
      "candidate": "free_lambda_rank_defect",
      "classification": "rank_inward",
      "delta_R_max_rg": 0.008807820986202586,
      "index": 71,
      "initial_H_R": 0.0004953979587164232,
      "initial_Omega_over_K": 0.9999968042984982,
      "initial_g_abs": 15057.131224098095,
      "initial_qadv_qvisc": 0.957889119691122,
      "initial_qrad_qvisc": 0.04211088031128379,
      "initial_qvisc_sign": 1.0,
      "max_H_R": 0.0005273967769947649,
      "max_abs_Omega_over_K": 1.0000333285808882,
      "max_p_x": 0.039735845041446456,
      "message": "completed s_max",
      "min_p_x": -0.058796530132355036,
      "min_qvisc_sign": -1.0,
      "min_smin_over_smax_B": 4.146322271794844e-09,
      "n_steps": 3001,
      "p_T_rank": 0.9605476470328533,
      "p_u_rank": 0.27463546074738715,
      "p_x_initial": 5.9494369647877754e-05,
      "p_x_rank": -0.04385865341890126,
      "p_x_sign_changes": 27,
      "s_end": 6.001999999999561,
      "step_failed": false,
      "target_reached": false
    },
    {
      "R_end_rg": 6.216023712505159,
      "R_max_rg": 6.223753168906898,
      "R_min_rg": 6.213737915433206,
      "R_start_rg": 6.219059393562907,
      "alpha": 6.197114275574386,
      "alpha_deg": 355.0684931506849,
      "candidate": "free_lambda_rank_defect",
      "classification": "rank_inward",
      "delta_R_max_rg": 0.004693775343990403,
      "index": 72,
      "initial_H_R": 0.0004953980126325908,
      "initial_Omega_over_K": 0.9999968040813468,
      "initial_g_abs": 10164.766485525048,
      "initial_qadv_qvisc": 0.9588716565618188,
      "initial_qrad_qvisc": 0.04112834343766067,
      "initial_qvisc_sign": 1.0,
      "max_H_R": 0.0005163657003855513,
      "max_abs_Omega_over_K": 1.0000188543057127,
      "max_p_x": 0.046648945071332604,
      "message": "completed s_max",
      "min_p_x": -0.05077430130860709,
      "min_qvisc_sign": 1.0,
      "min_smin_over_smax_B": 6.96939973436592e-09,
      "n_steps": 3001,
      "p_T_rank": 0.9806522939222196,
      "p_u_rank": 0.19097715504546547,
      "p_x_initial": 8.815742583614745e-05,
      "p_x_rank": -0.04299772872872244,
      "p_x_sign_changes": 82,
      "s_end": 6.001999999999561,
      "step_failed": false,
      "target_reached": false
    }
  ]
}
